rtl/alu.sv
`default_nettype none

module alu (
    input  wire  [31:0] a,
    input  wire  [31:0] b,
    input  wire  [ 1:0] alu_op,
    output logic [31:0] result
);

  localparam logic [1:0] OP_ADD = 2'b00;
  localparam logic [1:0] OP_SUB = 2'b01;
  localparam logic [1:0] OP_AND = 2'b10;
  localparam logic [1:0] OP_OR  = 2'b11;

  always_comb begin
    case (alu_op)
      OP_ADD:  result = a + b;
      OP_SUB:  result = a - b;
      OP_AND:  result = a & b;
      OP_OR:   result = a | b;
      default: result = 32'd0;
    endcase
  end

endmodule

rtl/vector_alu.sv
`default_nettype none

module vector_alu (
    input  wire  [3:0][31:0] a,
    input  wire  [3:0][31:0] b,
    input  wire  [1:0]       alu_op,
    output logic [3:0][31:0] result
);

  genvar i;
  generate
    for (i = 0; i < 4; i = i + 1) begin : g_alu_lanes
      alu alu_inst (
          .a(a[i]),
          .b(b[i]),
          .alu_op(alu_op),
          .result(result[i])
      );
    end
  endgenerate

endmodule

rtl/vector_regfile.sv
`default_nettype none

module vector_regfile (
    input wire             clk,
    input wire             we,
    input wire [2:0]       rs1,
    input wire [2:0]       rs2,
    input wire [2:0]       rd,
    input wire [3:0][31:0] wd,

    output logic [3:0][31:0] rd1_data,
    output logic [3:0][31:0] rd2_data
);

  logic [3:0][31:0] v_reg[8];

  always_ff @(posedge clk) begin
    if (we) begin
      v_reg[rd] <= wd;
    end
  end

  always_comb begin
    rd1_data = v_reg[rs1];
    rd2_data = v_reg[rs2];
  end

endmodule

rtl/simd_datapath.sv
`default_nettype none

module simd_datapath (
    input wire       clk,
    input wire       we,
    input wire [2:0] rs1,
    input wire [2:0] rs2,
    input wire [2:0] rd,
    input wire [1:0] alu_op,

    input wire             wb_sel,
    input wire [3:0][31:0] ext_data_in
);

  logic [3:0][31:0] alu_in_a;
  logic [3:0][31:0] alu_in_b;
  logic [3:0][31:0] alu_out;

  logic [3:0][31:0] write_back_data;

  always_comb begin
    if (wb_sel) begin
      write_back_data = ext_data_in;
    end else begin
      write_back_data = alu_out;
    end
  end

  vector_regfile reg_file_inst (
      .clk(clk),
      .we(we),
      .rs1(rs1),
      .rs2(rs2),
      .rd(rd),
      .wd(write_back_data),
      .rd1_data(alu_in_a),
      .rd2_data(alu_in_b)
  );

  vector_alu alu_inst (
      .a(alu_in_a),
      .b(alu_in_b),
      .alu_op(alu_op),
      .result(alu_out)
  );

endmodule

rtl/instruction_decoder.sv
`default_nettype none

module instruction_decoder (
    input wire [31:0] instr,

    output logic       we,
    output logic [2:0] rs1,
    output logic [2:0] rs2,
    output logic [2:0] rd,
    output logic [2:0] alu_op,
    output logic       wb_sel
);

  localparam logic [5:0] OPC_VADD  = 6'd1;
  localparam logic [5:0] OPC_VSUB  = 6'd2;
  localparam logic [5:0] OPC_VAND  = 6'd4;
  localparam logic [5:0] OPC_VOR   = 6'd8;
  localparam logic [5:0] OPC_VLOAD = 6'd16;

  logic [ 5:0] opcode;
  logic [16:0] imm;

  assign opcode = instr[31:26];
  assign rd     = instr[25:23];
  assign rs1    = instr[22:20];
  assign rs2    = instr[19:17];
  assign imm    = instr[16:0];

  always_comb begin
    we     = 1'b0;
    wb_sel = 1'b0;
    alu_op = 2'b00;

    case (opcode)
      OPC_VADD: begin
        we     = 1'b1;
        wb_sel = 1'b0;
        alu_op = 2'b00;
      end
      OPC_VSUB: begin
        we     = 1'b1;
        wb_sel = 1'b0;
        alu_op = 2'b01;
      end
      OPC_VAND: begin
        we     = 1'b1;
        wb_sel = 1'b0;
        alu_op = 2'b10;
      end
      OPC_VOR: begin
        we     = 1'b1;
        wb_sel = 1'b0;
        alu_op = 2'b11;
      end
      OPC_VLOAD: begin
        we     = 1'b1;
        wb_sel = 1'b1;
        alu_op = 2'b00;
      end
      default: begin
        we = 1'b0;
      end
    endcase
  end

endmodule

rtl/instruction_memory.sv
`default_nettype none

module instruction_memory (
    input  wire  [31:0] addr,
    output logic [31:0] instr
);

  logic [31:0] rom[32];

  initial begin
    // 1. VLOAD V1, 0, 0 (Hex: 0x4080_0000)
    rom[0] = 32'b010000_001_000_000_00000000000000000;

    // 2. VLOAD V2, 0, 0 (Hex: 0x4100_0000)
    rom[1] = 32'b010000_010_000_000_00000000000000000;

    // 3. VADD V3, V1, V2 (Hex: 0x04C8_0000)
    rom[2] = 32'b000001_011_001_010_00000000000000000;

    // 4. VSUB V4, V3, V2 (Hex: 0x0908_0000)
    rom[3] = 32'b000010_100_011_010_00000000000000000;

    for (int i = 4; i < 64; i++) begin
      rom[i] = 32'h0000_0000;
    end
  end

  always_comb begin
    logic [29:0] word_index;
    word_index = addr[31:2];

    if (word_index < 64) begin
      instr = rom[word_index];
    end else begin
      instr = 32'd0;
    end
  end

endmodule

rtl/program_counter.sv
`default_nettype none

module program_counter (
    input  wire         clk,
    input  wire         reset,
    output logic [31:0] pc
);

always_ff @(posedge clk) begin
  if (reset) begin
    pc <= 32'd0;
  end else begin
    pc <= pc + 32'd4;
  end
end

endmodule

rtl/simd_core.sv
`default_nettype none

module simd_core (
    input wire             clk,
    input wire             reset,
    input wire [3:0][31:0] ext_data_in
);

  logic        ctrl_we;
  logic [ 2:0] ctrl_rs1;
  logic [ 2:0] ctrl_rs2;
  logic [ 2:0] ctrl_rd;
  logic [ 2:0] ctrl_alu_op;
  logic        ctrl_wb_sel;

  logic [31:0] pc;
  logic [31:0] instr;

  program_counter pc_inst (
      .clk(clk),
      .reset(reset),
      .pc(pc)
  );

  instruction_memory rom_inst (
      .addr (pc),
      .instr(instr)
  );

  instruction_decoder id_inst (
      .instr(instr),
      .we(ctrl_we),
      .rs1(ctrl_rs1),
      .rs2(ctrl_rs2),
      .rd(ctrl_rd),
      .alu_op(ctrl_alu_op),
      .wb_sel(ctrl_wb_sel)
  );

  simd_datapath datapath_inst (
      .clk(clk),
      .we(ctrl_we),
      .rs1(ctrl_rs1),
      .rs2(ctrl_rs2),
      .rd(ctrl_rd),
      .alu_op(ctrl_alu_op),
      .wb_sel(ctrl_wb_sel),
      .ext_data_in(ext_data_in)
  );

endmodule

tb/simd_core_tb.sv
`default_nettype none
`timescale 1ns / 1ps

module simd_core_tb;

  // 1. Declare Signals
  logic             clk;
  logic             reset;
  logic [3:0][31:0] ext_data_in;

  // 2. Instantiate the CPU
  simd_core dut (.*);

  // 3. Clock Generation (100 MHz)
  initial begin
    clk = 0;
    forever #5 clk = ~clk;
  end

  // 4. The Boot Sequence
  initial begin
    $dumpfile("sim/simd_core.vcd");
    $dumpvars(0, simd_core_tb);

    // Dump internal registers so we can see them in GTKWave
    for (int k = 0; k < 8; k++) begin
      $dumpvars(0, dut.datapath_inst.reg_file_inst.v_reg[k]);
    end

    // --- PHASE 1: SYSTEM RESET ---
    // Turn the reset line ON to clear the Program Counter
    reset       = 1'b1;
    ext_data_in = '0;

    // Hold reset for 20ns to let the silicon stabilize
    #20;

    // --- PHASE 2: BOOT UP ---
    // Release reset on the negative edge. The CPU wakes up and starts fetching!
    @(negedge clk);
    reset          = 1'b0;

    // Cycle 1: PC is 0. ROM outputs VLOAD V1. 
    // We feed the external bus with the data it expects to load.
    ext_data_in[0] = 32'd10;
    ext_data_in[1] = 32'd20;
    ext_data_in[2] = 32'd30;
    ext_data_in[3] = 32'd40;

    // Cycle 2: PC is 4. ROM outputs VLOAD V2.
    // Change the external data bus for the next load.
    @(negedge clk);
    ext_data_in[0] = 32'd5;
    ext_data_in[1] = 32'd5;
    ext_data_in[2] = 32'd5;
    ext_data_in[3] = 32'd5;

    // Cycle 3: PC is 8. ROM outputs VADD V3, V1, V2.
    // Cycle 4: PC is 12. ROM outputs VSUB V4, V3, V2.
    // Since the CPU is doing math, it ignores ext_data_in. We just let it run.
    #50;

    // --- PHASE 3: VERIFY ---
    $display("\n--- AUTONOMOUS EXECUTION COMPLETE ---");
    $display("V1 (Loaded) : %0d, %0d, %0d, %0d", dut.datapath_inst.reg_file_inst.v_reg[1][0],
             dut.datapath_inst.reg_file_inst.v_reg[1][1],
             dut.datapath_inst.reg_file_inst.v_reg[1][2],
             dut.datapath_inst.reg_file_inst.v_reg[1][3]);

    $display("V3 (V1 + V2): %0d, %0d, %0d, %0d", dut.datapath_inst.reg_file_inst.v_reg[3][0],
             dut.datapath_inst.reg_file_inst.v_reg[3][1],
             dut.datapath_inst.reg_file_inst.v_reg[3][2],
             dut.datapath_inst.reg_file_inst.v_reg[3][3]);

    $display("V4 (V3 - V2): %0d, %0d, %0d, %0d", dut.datapath_inst.reg_file_inst.v_reg[4][0],
             dut.datapath_inst.reg_file_inst.v_reg[4][1],
             dut.datapath_inst.reg_file_inst.v_reg[4][2],
             dut.datapath_inst.reg_file_inst.v_reg[4][3]);

    $finish;
  end

endmodule

sim/simd_core.vcd
$date
	Fri Sep  4 21:57:31 2026
$end
$version
	Icarus Verilog
$end
$timescale
	1ps
$end
$scope module simd_core_tb $end
$var reg 1 ! clk $end
$var reg 128 " ext_data_in [127:0] $end
$var reg 1 # reset $end
$scope module dut $end
$var wire 1 ! clk $end
$var wire 128 $ ext_data_in [127:0] $end
$var wire 1 # reset $end
$var wire 32 % pc [31:0] $end
$var wire 32 & instr [31:0] $end
$var wire 1 ' ctrl_we $end
$var wire 1 ( ctrl_wb_sel $end
$var wire 3 ) ctrl_rs2 [2:0] $end
$var wire 3 * ctrl_rs1 [2:0] $end
$var wire 3 + ctrl_rd [2:0] $end
$var wire 3 , ctrl_alu_op [2:0] $end
$scope module datapath_inst $end
$var wire 2 - alu_op [1:0] $end
$var wire 1 ! clk $end
$var wire 128 . ext_data_in [127:0] $end
$var wire 1 ' we $end
$var wire 1 ( wb_sel $end
$var wire 3 / rs2 [2:0] $end
$var wire 3 0 rs1 [2:0] $end
$var wire 3 1 rd [2:0] $end
$var wire 128 2 alu_out [127:0] $end
$var wire 128 3 alu_in_b [127:0] $end
$var wire 128 4 alu_in_a [127:0] $end
$var reg 128 5 write_back_data [127:0] $end
$scope module alu_inst $end
$var wire 2 6 alu_op [1:0] $end
$var wire 128 7 result [127:0] $end
$var wire 128 8 b [127:0] $end
$var wire 128 9 a [127:0] $end
$scope begin g_alu_lanes[0] $end
$var parameter 2 : i $end
$scope module alu_inst $end
$var wire 32 ; a [31:0] $end
$var wire 2 < alu_op [1:0] $end
$var wire 32 = b [31:0] $end
$var parameter 2 > OP_ADD $end
$var parameter 2 ? OP_AND $end
$var parameter 2 @ OP_OR $end
$var parameter 2 A OP_SUB $end
$var reg 32 B result [31:0] $end
$upscope $end
$upscope $end
$scope begin g_alu_lanes[1] $end
$var parameter 2 C i $end
$scope module alu_inst $end
$var wire 32 D a [31:0] $end
$var wire 2 E alu_op [1:0] $end
$var wire 32 F b [31:0] $end
$var parameter 2 G OP_ADD $end
$var parameter 2 H OP_AND $end
$var parameter 2 I OP_OR $end
$var parameter 2 J OP_SUB $end
$var reg 32 K result [31:0] $end
$upscope $end
$upscope $end
$scope begin g_alu_lanes[2] $end
$var parameter 3 L i $end
$scope module alu_inst $end
$var wire 32 M a [31:0] $end
$var wire 2 N alu_op [1:0] $end
$var wire 32 O b [31:0] $end
$var parameter 2 P OP_ADD $end
$var parameter 2 Q OP_AND $end
$var parameter 2 R OP_OR $end
$var parameter 2 S OP_SUB $end
$var reg 32 T result [31:0] $end
$upscope $end
$upscope $end
$scope begin g_alu_lanes[3] $end
$var parameter 3 U i $end
$scope module alu_inst $end
$var wire 32 V a [31:0] $end
$var wire 2 W alu_op [1:0] $end
$var wire 32 X b [31:0] $end
$var parameter 2 Y OP_ADD $end
$var parameter 2 Z OP_AND $end
$var parameter 2 [ OP_OR $end
$var parameter 2 \ OP_SUB $end
$var reg 32 ] result [31:0] $end
$upscope $end
$upscope $end
$upscope $end
$scope module reg_file_inst $end
$var wire 1 ! clk $end
$var wire 128 ^ wd [127:0] $end
$var wire 1 ' we $end
$var wire 3 _ rs2 [2:0] $end
$var wire 3 ` rs1 [2:0] $end
$var wire 3 a rd [2:0] $end
$var reg 128 b rd1_data [127:0] $end
$var reg 128 c rd2_data [127:0] $end
$upscope $end
$upscope $end
$scope module id_inst $end
$var wire 3 d rs2 [2:0] $end
$var wire 3 e rs1 [2:0] $end
$var wire 3 f rd [2:0] $end
$var wire 6 g opcode [5:0] $end
$var wire 32 h instr [31:0] $end
$var wire 17 i imm [16:0] $end
$var parameter 6 j OPC_VADD $end
$var parameter 6 k OPC_VAND $end
$var parameter 6 l OPC_VLOAD $end
$var parameter 6 m OPC_VOR $end
$var parameter 6 n OPC_VSUB $end
$var reg 3 o alu_op [2:0] $end
$var reg 1 ( wb_sel $end
$var reg 1 ' we $end
$upscope $end
$scope module pc_inst $end
$var wire 1 ! clk $end
$var wire 1 # reset $end
$var reg 32 p pc [31:0] $end
$upscope $end
$scope module rom_inst $end
$var wire 32 q addr [31:0] $end
$var reg 32 r instr [31:0] $end
$scope begin $ivl_for_loop0 $end
$var integer 32 s i [31:0] $end
$upscope $end
$scope begin $unm_blk_11 $end
$var reg 30 t word_index [29:0] $end
$upscope $end
$upscope $end
$upscope $end
$scope begin $ivl_for_loop1 $end
$var integer 32 u k [31:0] $end
$upscope $end
$upscope $end
$scope module simd_core_tb $end
$scope module dut $end
$scope module datapath_inst $end
$scope module reg_file_inst $end
$var reg 128 v \v_reg[0] [127:0] $end
$upscope $end
$upscope $end
$upscope $end
$upscope $end
$scope module simd_core_tb $end
$scope module dut $end
$scope module datapath_inst $end
$scope module reg_file_inst $end
$var reg 128 w \v_reg[1] [127:0] $end
$upscope $end
$upscope $end
$upscope $end
$upscope $end
$scope module simd_core_tb $end
$scope module dut $end
$scope module datapath_inst $end
$scope module reg_file_inst $end
$var reg 128 x \v_reg[2] [127:0] $end
$upscope $end
$upscope $end
$upscope $end
$upscope $end
$scope module simd_core_tb $end
$scope module dut $end
$scope module datapath_inst $end
$scope module reg_file_inst $end
$var reg 128 y \v_reg[3] [127:0] $end
$upscope $end
$upscope $end
$upscope $end
$upscope $end
$scope module simd_core_tb $end
$scope module dut $end
$scope module datapath_inst $end
$scope module reg_file_inst $end
$var reg 128 z \v_reg[4] [127:0] $end
$upscope $end
$upscope $end
$upscope $end
$upscope $end
$scope module simd_core_tb $end
$scope module dut $end
$scope module datapath_inst $end
$scope module reg_file_inst $end
$var reg 128 { \v_reg[5] [127:0] $end
$upscope $end
$upscope $end
$upscope $end
$upscope $end
$scope module simd_core_tb $end
$scope module dut $end
$scope module datapath_inst $end
$scope module reg_file_inst $end
$var reg 128 | \v_reg[6] [127:0] $end
$upscope $end
$upscope $end
$upscope $end
$upscope $end
$scope module simd_core_tb $end
$scope module dut $end
$scope module datapath_inst $end
$scope module reg_file_inst $end
$var reg 128 } \v_reg[7] [127:0] $end
$upscope $end
$upscope $end
$upscope $end
$upscope $end
$enddefinitions $end
$comment Show the parameter values. $end
$dumpall
b10 n
b1000 m
b10000 l
b100 k
b1 j
b1 \
b11 [
b10 Z
b0 Y
b11 U
b1 S
b11 R
b10 Q
b0 P
b10 L
b1 J
b11 I
b10 H
b0 G
b1 C
b1 A
b11 @
b10 ?
b0 >
b0 :
$end
#0
$dumpvars
bx }
bx |
bx {
bx z
bx y
bx x
bx w
bx v
b1000 u
bx t
b1000000 s
b0 r
bx q
bx p
b0 o
b0 i
b0 h
b0 g
b0 f
b0 e
b0 d
bx c
bx b
b0 a
b0 `
b0 _
bx ^
bx ]
bx X
b0 W
bx V
bx T
bx O
b0 N
bx M
bx K
bx F
b0 E
bx D
bx B
bx =
b0 <
bx ;
bx 9
bx 8
bx 7
b0 6
bx 5
bx 4
bx 3
bx 2
b0 1
b0 0
b0 /
b0 .
b0 -
b0 ,
b0 +
b0 *
b0 )
0(
0'
b0 &
bx %
b0 $
1#
b0 "
0!
$end
#5000
b0 5
b0 ^
1(
1'
b1 +
b1 1
b1 a
b1 f
b10000 g
b1000000100000000000000000000000 &
b1000000100000000000000000000000 h
b1000000100000000000000000000000 r
b0 t
b0 %
b0 p
b0 q
1!
#10000
0!
#15000
b0 w
1!
#20000
b101000000000000000000000000000000111100000000000000000000000000001010000000000000000000000000000001010 5
b101000000000000000000000000000000111100000000000000000000000000001010000000000000000000000000000001010 ^
b101000000000000000000000000000000111100000000000000000000000000001010000000000000000000000000000001010 "
b101000000000000000000000000000000111100000000000000000000000000001010000000000000000000000000000001010 $
b101000000000000000000000000000000111100000000000000000000000000001010000000000000000000000000000001010 .
0#
0!
#25000
b10 +
b10 1
b10 a
b10 f
b1000001000000000000000000000000 &
b1000001000000000000000000000000 h
b1000001000000000000000000000000 r
b1 t
b100 %
b100 p
b100 q
b101000000000000000000000000000000111100000000000000000000000000001010000000000000000000000000000001010 w
1!
#30000
b101000000000000000000000000000001010000000000000000000000000000010100000000000000000000000000000101 5
b101000000000000000000000000000001010000000000000000000000000000010100000000000000000000000000000101 ^
b101000000000000000000000000000001010000000000000000000000000000010100000000000000000000000000000101 "
b101000000000000000000000000000001010000000000000000000000000000010100000000000000000000000000000101 $
b101000000000000000000000000000001010000000000000000000000000000010100000000000000000000000000000101 .
0!
#35000
b101101 ]
b100011 T
b11001 K
b101101000000000000000000000000001000110000000000000000000000000001100100000000000000000000000000001111 2
b101101000000000000000000000000001000110000000000000000000000000001100100000000000000000000000000001111 7
b1111 B
b101 X
b101 O
b101 F
b101 =
b101000 V
b11110 M
b10100 D
b1010 ;
b101101000000000000000000000000001000110000000000000000000000000001100100000000000000000000000000001111 5
b101101000000000000000000000000001000110000000000000000000000000001100100000000000000000000000000001111 ^
b101000000000000000000000000000001010000000000000000000000000000010100000000000000000000000000000101 3
b101000000000000000000000000000001010000000000000000000000000000010100000000000000000000000000000101 8
b101000000000000000000000000000001010000000000000000000000000000010100000000000000000000000000000101 c
b101000000000000000000000000000000111100000000000000000000000000001010000000000000000000000000000001010 4
b101000000000000000000000000000000111100000000000000000000000000001010000000000000000000000000000001010 9
b101000000000000000000000000000000111100000000000000000000000000001010000000000000000000000000000001010 b
0(
1'
b10 )
b10 /
b10 _
b10 d
b1 *
b1 0
b1 `
b1 e
b11 +
b11 1
b11 a
b11 f
b1 g
b101100101000000000000000000 &
b101100101000000000000000000 h
b101100101000000000000000000 r
b10 t
b101000000000000000000000000000001010000000000000000000000000000010100000000000000000000000000000101 x
b1000 %
b1000 p
b1000 q
1!
#40000
0!
#45000
b101000000000000000000000000000000111100000000000000000000000000001010000000000000000000000000000001010 5
b101000000000000000000000000000000111100000000000000000000000000001010000000000000000000000000000001010 ^
b1010 B
b10100 K
b11110 T
b101000000000000000000000000000000111100000000000000000000000000001010000000000000000000000000000001010 2
b101000000000000000000000000000000111100000000000000000000000000001010000000000000000000000000000001010 7
b101000 ]
b101101 V
b100011 M
b11001 D
b1111 ;
b1 -
b1 6
b1 <
b1 E
b1 N
b1 W
b101101000000000000000000000000001000110000000000000000000000000001100100000000000000000000000000001111 4
b101101000000000000000000000000001000110000000000000000000000000001100100000000000000000000000000001111 9
b101101000000000000000000000000001000110000000000000000000000000001100100000000000000000000000000001111 b
b1 ,
b1 o
1'
b11 *
b11 0
b11 `
b11 e
b100 +
b100 1
b100 a
b100 f
b10 g
b1010001101000000000000000000 &
b1010001101000000000000000000 h
b1010001101000000000000000000 r
b11 t
b1100 %
b1100 p
b1100 q
b101101000000000000000000000000001000110000000000000000000000000001100100000000000000000000000000001111 y
1!
#50000
0!
#55000
bx 5
bx ^
bx B
bx K
bx T
bx 2
bx 7
bx ]
bx X
bx O
bx F
bx =
bx V
bx M
bx D
bx ;
b0 -
b0 6
b0 <
b0 E
b0 N
b0 W
bx 3
bx 8
bx c
bx 4
bx 9
bx b
b0 ,
b0 o
0'
b0 )
b0 /
b0 _
b0 d
b0 *
b0 0
b0 `
b0 e
b0 +
b0 1
b0 a
b0 f
b0 g
b0 &
b0 h
b0 r
b100 t
b101000000000000000000000000000000111100000000000000000000000000001010000000000000000000000000000001010 z
b10000 %
b10000 p
b10000 q
1!
#60000
0!
#65000
b101 t
b10100 %
b10100 p
b10100 q
1!
#70000
0!
#75000
b110 t
b11000 %
b11000 p
b11000 q
1!
