rtl/data_memory.sv
`default_nettype none

module data_memory (
    input  wire               clk,
    input  wire               we,
    input  wire  [31:0]       address,
    input  wire  [ 3:0][31:0] data_in,
    output logic [ 3:0][31:0] data_out
);

  logic [ 3:0][31:0] sram       [256];
  logic [27:0]       word_index;

  assign word_index = address[31:4];

  initial begin
    for (int i = 0; i < 256; i++) begin
      sram[i] = '0;
    end
  end

  // synchronous writes on clock pos edge
  always_ff @(posedge clk) begin
    if (we && (word_index < 256)) begin
      sram[word_index] <= data_in;
    end
  end

  // asynchronous reads
  always_comb begin
    if (word_index < 256) begin
      data_out = sram[word_index];
    end else begin
      data_out = '0;
    end
  end

endmodule

rtl/alu.sv
`default_nettype none

module alu (
    input  wire  [31:0] a,
    input  wire  [31:0] b,
    input  wire  [ 1:0] alu_op,
    output logic [31:0] result,
    output logic        is_zero
);

  localparam logic [1:0] OP_ADD = 2'b00;
  localparam logic [1:0] OP_SUB = 2'b01;
  localparam logic [1:0] OP_AND = 2'b10;
  localparam logic [1:0] OP_OR  = 2'b11;

  always_comb begin
    case (alu_op)
      OP_ADD:  result = a + b;
      OP_SUB:  result = a - b;
      OP_AND:  result = a & b;
      OP_OR:   result = a | b;
      default: result = 32'd0;

    endcase
  end


endmodule

rtl/vector_alu.sv
`default_nettype none

module vector_alu (
    input  wire  [3:0][31:0] a,
    input  wire  [3:0][31:0] b,
    input  wire  [1:0]       alu_op,
    output logic [3:0][31:0] result,
    output logic             is_zero
);

  genvar i;
  generate
    for (i = 0; i < 4; i = i + 1) begin : g_alu_lanes
      alu alu_inst (
          .a(a[i]),
          .b(b[i]),
          .alu_op(alu_op),
          .result(result[i])
      );
    end
  endgenerate

  always_comb begin
    if (result == 128'd0) begin
      is_zero = 1'b1;
    end else begin
      is_zero = 1'b0;
    end
  end
endmodule

rtl/vector_regfile.sv
`default_nettype none

module vector_regfile (
    input wire             clk,
    input wire             we,
    input wire [2:0]       rs1,
    input wire [2:0]       rs2,
    input wire [2:0]       rd,
    input wire [3:0][31:0] wd,

    output logic [3:0][31:0] rd1_data,
    output logic [3:0][31:0] rd2_data
);

  logic [3:0][31:0] v_reg[8];

  always_ff @(posedge clk) begin
    if (we) begin
      v_reg[rd] <= wd;
    end
  end

  always_comb begin
    rd1_data = v_reg[rs1];
    rd2_data = v_reg[rs2];
  end

endmodule

rtl/simd_datapath.sv
`default_nettype none

module simd_datapath (
    input wire       clk,
    input wire       we,
    input wire [2:0] rs1,
    input wire [2:0] rs2,
    input wire [2:0] rd,
    input wire [1:0] alu_op,

    input wire wb_sel,

    input  wire  [3:0][31:0] mem_data_out,  // data coming from sram
    output logic [3:0][31:0] mem_data_in,   // data going to sram

    output logic is_zero
);

  logic [3:0][31:0] alu_in_a;
  logic [3:0][31:0] alu_in_b;
  logic [3:0][31:0] alu_out;
  logic [3:0][31:0] write_back_data;

  assign mem_data_in = alu_in_a;

  always_comb begin
    if (wb_sel) begin
      write_back_data = mem_data_out;
    end else begin
      write_back_data = alu_out;
    end
  end

  vector_regfile reg_file_inst (
      .clk(clk),
      .we(we),
      .rs1(rs1),
      .rs2(rs2),
      .rd(rd),
      .wd(write_back_data),
      .rd1_data(alu_in_a),
      .rd2_data(alu_in_b)
  );

  vector_alu alu_inst (
      .a(alu_in_a),
      .b(alu_in_b),
      .alu_op(alu_op),
      .result(alu_out),
      .is_zero(is_zero)
  );

endmodule

rtl/instruction_decoder.sv
`default_nettype none

module instruction_decoder (
    input wire [31:0] instr,

    // datapath control
    output logic       we,
    output logic [2:0] rs1,
    output logic [2:0] rs2,
    output logic [2:0] rd,
    output logic [1:0] alu_op,
    output logic       wb_sel,

    // branch control
    output logic        branch,
    output logic [16:0] imm,

    // sram memory control
    output logic mem_we
);

  localparam logic [5:0] OPC_VADD  = 6'b000001;
  localparam logic [5:0] OPC_VSUB  = 6'b000010;
  localparam logic [5:0] OPC_VAND  = 6'b000100;
  localparam logic [5:0] OPC_VOR   = 6'b001000;
  localparam logic [5:0] OPC_VLOAD = 6'b010000;
  localparam logic [5:0] OPC_VSTR  = 6'b010001;
  localparam logic [5:0] OPC_BEQ   = 6'b110000;

  logic [5:0] opcode;

  assign opcode = instr[31:26];
  assign rd     = instr[25:23];
  assign rs1    = instr[22:20];
  assign rs2    = instr[19:17];
  assign imm    = instr[16:0];

  always_comb begin
    we     = 1'b0;
    wb_sel = 1'b0;
    alu_op = 2'b00;
    branch = 1'b0;
    mem_we = 1'b0;

    case (opcode)
      OPC_VADD: begin
        we     = 1'b1;
        wb_sel = 1'b0;
        alu_op = 2'b00;
      end
      OPC_VSUB: begin
        we     = 1'b1;
        wb_sel = 1'b0;
        alu_op = 2'b01;
      end
      OPC_VAND: begin
        we     = 1'b1;
        wb_sel = 1'b0;
        alu_op = 2'b10;
      end
      OPC_VOR: begin
        we     = 1'b1;
        wb_sel = 1'b0;
        alu_op = 2'b11;
      end
      OPC_VLOAD: begin
        we     = 1'b1;
        wb_sel = 1'b1;
        alu_op = 2'b00;
        mem_we = 1'b0;
      end
      OPC_VSTR: begin
        we     = 1'b0;
        wb_sel = 1'b0;
        alu_op = 2'b00;
        mem_we = 1'b1;
      end
      OPC_BEQ: begin
        we     = 1'b0;
        wb_sel = 1'b1;
        alu_op = 2'b01;
        branch = 1'b1;
      end

      default: begin
        we = 1'b0;
      end
    endcase
  end

endmodule

rtl/instruction_memory.sv
`default_nettype none

module instruction_memory (
    input  wire  [31:0] addr,
    output logic [31:0] instr
);

  logic [31:0] rom[64];

  initial begin
    // [0] PC = 0: VLOAD V1, Addr 0
    rom[0] = {6'b010000, 3'd1, 3'd0, 3'd0, 17'd0};

    // [1] PC = 4: VLOAD V2, Addr 16
    rom[1] = {6'b010000, 3'd2, 3'd0, 3'd0, 17'd16};

    // [2] PC = 8: VADD V3, V1, V2
    rom[2] = {6'b000001, 3'd3, 3'd1, 3'd2, 17'd0};

    // [3] PC = 12: VSTR V3, Addr 32 (Source data is in rs1)
    rom[3] = {6'b010001, 3'd0, 3'd3, 3'd0, 17'd32};

    // [4] PC = 16: BEQ V1, V1, +0 (Infinite loop / Halt)
    rom[4] = {6'b110000, 3'd0, 3'd1, 3'd1, 17'd0};

    // Pad remaining slots
    for (int i = 5; i < 64; i++) begin
      rom[i] = 32'h0000_0000;
    end
  end

  logic [29:0] word_index;
  assign word_index = addr[31:2];

  always_comb begin
    if (word_index < 64) begin
      instr = rom[word_index];
    end else begin
      instr = 32'h0000_0000;
    end
  end

endmodule

rtl/program_counter.sv
`default_nettype none

module program_counter (
    input wire clk,
    input wire reset,

    input wire        branch,
    input wire [16:0] imm,
    input wire        is_zero,

    output logic [31:0] pc
);

  logic [31:0] extended_imm;
  assign extended_imm = {{15{imm[16]}}, imm};

  always_ff @(posedge clk) begin
    if (reset) begin
      pc <= 32'd0;
    end else begin
      if (branch && is_zero) begin
        pc <= pc + extended_imm;
      end else begin
        pc <= pc + 32'd4;
      end
    end
  end

endmodule

rtl/simd_core.sv
`default_nettype none

module simd_core (
    input wire clk,
    input wire reset
);

  logic              ctrl_we;
  logic [ 2:0]       ctrl_rs1;
  logic [ 2:0]       ctrl_rs2;
  logic [ 2:0]       ctrl_rd;
  logic [ 1:0]       ctrl_alu_op;
  logic              ctrl_wb_sel;

  logic              ctrl_is_zero;
  logic              ctrl_branch;

  logic              ctrl_mem_we;

  logic [31:0]       pc;
  logic [31:0]       instr;

  logic [16:0]       imm;

  logic [ 3:0][31:0] mem_to_datapath;
  logic [ 3:0][31:0] datapath_to_mem;

  program_counter pc_inst (
      .clk(clk),
      .reset(reset),
      .pc(pc),
      .branch(ctrl_branch),
      .imm(imm),
      .is_zero(ctrl_is_zero)
  );

  instruction_memory rom_inst (
      .addr (pc),
      .instr(instr)
  );

  instruction_decoder id_inst (
      .instr(instr),
      .we(ctrl_we),
      .rs1(ctrl_rs1),
      .rs2(ctrl_rs2),
      .rd(ctrl_rd),
      .alu_op(ctrl_alu_op),
      .wb_sel(ctrl_wb_sel),
      .branch(ctrl_branch),
      .imm(imm),
      .mem_we(ctrl_mem_we)
  );

  simd_datapath datapath_inst (
      .clk(clk),
      .we(ctrl_we),
      .rs1(ctrl_rs1),
      .rs2(ctrl_rs2),
      .rd(ctrl_rd),
      .alu_op(ctrl_alu_op),
      .mem_data_out(mem_to_datapath),
      .mem_data_in(datapath_to_mem),
      .wb_sel(ctrl_wb_sel),
      .is_zero(ctrl_is_zero)
  );

  data_memory ram_inst (
      .clk(clk),
      .we(ctrl_mem_we),
      .address({15'b0, imm}),
      .data_in(datapath_to_mem),
      .data_out(mem_to_datapath)
  );

endmodule

tb/simd_core_tb.sv
`default_nettype none
`timescale 1ns / 1ps

module simd_core_tb;

  logic clk;
  logic reset;

  // The fully self-contained CPU
  simd_core dut (
      .clk  (clk),
      .reset(reset)
  );

  // 100 MHz clock
  initial begin
    clk = 0;
    forever #5 clk = ~clk;
  end

  initial begin
    $dumpfile("sim/simd_core.vcd");
    $dumpvars(0, simd_core_tb);

    // Dump register file and SRAM memory slots for inspection
    for (int k = 0; k < 8; k++) begin
      $dumpvars(0, dut.datapath_inst.reg_file_inst.v_reg[k]);
    end
    $dumpvars(0, dut.ram_inst.sram[0]);
    $dumpvars(0, dut.ram_inst.sram[1]);
    $dumpvars(0, dut.ram_inst.sram[2]);  // This is Address 32

    $display("\n==========================================");
    $display("BOOTING SIMD MICROPROCESSOR");
    $display("==========================================");

    // 1. Hold reset high
    reset                   = 1'b1;

    // 2. Pre-load the Data RAM (Simulating a Bootloader)
    // sram[0] corresponds to address 0
    dut.ram_inst.sram[0][0] = 32'd10;
    dut.ram_inst.sram[0][1] = 32'd20;
    dut.ram_inst.sram[0][2] = 32'd30;
    dut.ram_inst.sram[0][3] = 32'd40;

    // sram[1] corresponds to address 16
    dut.ram_inst.sram[1][0] = 32'd5;
    dut.ram_inst.sram[1][1] = 32'd5;
    dut.ram_inst.sram[1][2] = 32'd5;
    dut.ram_inst.sram[1][3] = 32'd5;

    #20;

    // 3. Release reset. The CPU is now completely autonomous.
    @(negedge clk);
    reset = 1'b0;

    // 4. Give the CPU exactly 6 clock cycles to run the 5-instruction program
    #60;

    $display("CPU HALTED. Inspecting SRAM Address 32 (sram[2]):");
    $display("Expected: 15, 25, 35, 45");
    $display("Actual:   %0d, %0d, %0d, %0d", dut.ram_inst.sram[2][0], dut.ram_inst.sram[2][1],
             dut.ram_inst.sram[2][2], dut.ram_inst.sram[2][3]);

    $finish;
  end

endmodule

sim/simd_core.vcd
$date
	Wed Oct  7 00:47:34 2026
$end
$version
	Icarus Verilog
$end
$timescale
	1ps
$end
$scope module simd_core_tb $end
$var reg 1 ! clk $end
$var reg 1 " reset $end
$scope module dut $end
$var wire 1 ! clk $end
$var wire 1 " reset $end
$var wire 32 # pc [31:0] $end
$var wire 128 $ mem_to_datapath [127:0] $end
$var wire 32 % instr [31:0] $end
$var wire 17 & imm [16:0] $end
$var wire 128 ' datapath_to_mem [127:0] $end
$var wire 1 ( ctrl_we $end
$var wire 1 ) ctrl_wb_sel $end
$var wire 3 * ctrl_rs2 [2:0] $end
$var wire 3 + ctrl_rs1 [2:0] $end
$var wire 3 , ctrl_rd [2:0] $end
$var wire 1 - ctrl_mem_we $end
$var wire 1 . ctrl_is_zero $end
$var wire 1 / ctrl_branch $end
$var wire 2 0 ctrl_alu_op [1:0] $end
$scope module datapath_inst $end
$var wire 1 ! clk $end
$var wire 128 1 mem_data_in [127:0] $end
$var wire 1 ( we $end
$var wire 1 ) wb_sel $end
$var wire 3 2 rs2 [2:0] $end
$var wire 3 3 rs1 [2:0] $end
$var wire 3 4 rd [2:0] $end
$var wire 128 5 mem_data_out [127:0] $end
$var wire 1 . is_zero $end
$var wire 128 6 alu_out [127:0] $end
$var wire 2 7 alu_op [1:0] $end
$var wire 128 8 alu_in_b [127:0] $end
$var wire 128 9 alu_in_a [127:0] $end
$var reg 128 : write_back_data [127:0] $end
$scope module alu_inst $end
$var wire 128 ; result [127:0] $end
$var wire 128 < b [127:0] $end
$var wire 2 = alu_op [1:0] $end
$var wire 128 > a [127:0] $end
$var reg 1 . is_zero $end
$scope begin g_alu_lanes[0] $end
$var parameter 2 ? i $end
$scope module alu_inst $end
$var wire 32 @ a [31:0] $end
$var wire 32 A b [31:0] $end
$var wire 2 B alu_op [1:0] $end
$var parameter 2 C OP_ADD $end
$var parameter 2 D OP_AND $end
$var parameter 2 E OP_OR $end
$var parameter 2 F OP_SUB $end
$var reg 1 G is_zero $end
$var reg 32 H result [31:0] $end
$upscope $end
$upscope $end
$scope begin g_alu_lanes[1] $end
$var parameter 2 I i $end
$scope module alu_inst $end
$var wire 32 J a [31:0] $end
$var wire 32 K b [31:0] $end
$var wire 2 L alu_op [1:0] $end
$var parameter 2 M OP_ADD $end
$var parameter 2 N OP_AND $end
$var parameter 2 O OP_OR $end
$var parameter 2 P OP_SUB $end
$var reg 1 Q is_zero $end
$var reg 32 R result [31:0] $end
$upscope $end
$upscope $end
$scope begin g_alu_lanes[2] $end
$var parameter 3 S i $end
$scope module alu_inst $end
$var wire 32 T a [31:0] $end
$var wire 32 U b [31:0] $end
$var wire 2 V alu_op [1:0] $end
$var parameter 2 W OP_ADD $end
$var parameter 2 X OP_AND $end
$var parameter 2 Y OP_OR $end
$var parameter 2 Z OP_SUB $end
$var reg 1 [ is_zero $end
$var reg 32 \ result [31:0] $end
$upscope $end
$upscope $end
$scope begin g_alu_lanes[3] $end
$var parameter 3 ] i $end
$scope module alu_inst $end
$var wire 32 ^ a [31:0] $end
$var wire 32 _ b [31:0] $end
$var wire 2 ` alu_op [1:0] $end
$var parameter 2 a OP_ADD $end
$var parameter 2 b OP_AND $end
$var parameter 2 c OP_OR $end
$var parameter 2 d OP_SUB $end
$var reg 1 e is_zero $end
$var reg 32 f result [31:0] $end
$upscope $end
$upscope $end
$upscope $end
$scope module reg_file_inst $end
$var wire 1 ! clk $end
$var wire 128 g wd [127:0] $end
$var wire 1 ( we $end
$var wire 3 h rs2 [2:0] $end
$var wire 3 i rs1 [2:0] $end
$var wire 3 j rd [2:0] $end
$var reg 128 k rd1_data [127:0] $end
$var reg 128 l rd2_data [127:0] $end
$upscope $end
$upscope $end
$scope module id_inst $end
$var wire 3 m rs2 [2:0] $end
$var wire 3 n rs1 [2:0] $end
$var wire 3 o rd [2:0] $end
$var wire 6 p opcode [5:0] $end
$var wire 32 q instr [31:0] $end
$var wire 17 r imm [16:0] $end
$var parameter 6 s OPC_BEQ $end
$var parameter 6 t OPC_VADD $end
$var parameter 6 u OPC_VAND $end
$var parameter 6 v OPC_VLOAD $end
$var parameter 6 w OPC_VOR $end
$var parameter 6 x OPC_VSTR $end
$var parameter 6 y OPC_VSUB $end
$var reg 2 z alu_op [1:0] $end
$var reg 1 / branch $end
$var reg 1 - mem_we $end
$var reg 1 ) wb_sel $end
$var reg 1 ( we $end
$upscope $end
$scope module pc_inst $end
$var wire 1 / branch $end
$var wire 1 ! clk $end
$var wire 17 { imm [16:0] $end
$var wire 1 . is_zero $end
$var wire 1 " reset $end
$var wire 32 | extended_imm [31:0] $end
$var reg 32 } pc [31:0] $end
$upscope $end
$scope module ram_inst $end
$var wire 32 ~ address [31:0] $end
$var wire 1 ! clk $end
$var wire 128 !" data_in [127:0] $end
$var wire 1 - we $end
$var wire 28 "" word_index [27:0] $end
$var reg 128 #" data_out [127:0] $end
$scope begin $ivl_for_loop0 $end
$var integer 32 $" i [31:0] $end
$upscope $end
$upscope $end
$scope module rom_inst $end
$var wire 32 %" addr [31:0] $end
$var wire 30 &" word_index [29:0] $end
$var reg 32 '" instr [31:0] $end
$scope begin $ivl_for_loop1 $end
$var integer 32 (" i [31:0] $end
$upscope $end
$upscope $end
$upscope $end
$scope begin $ivl_for_loop2 $end
$var integer 32 )" k [31:0] $end
$upscope $end
$upscope $end
$scope module simd_core_tb $end
$scope module dut $end
$scope module datapath_inst $end
$scope module reg_file_inst $end
$var reg 128 *" \v_reg[0] [127:0] $end
$upscope $end
$upscope $end
$upscope $end
$upscope $end
$scope module simd_core_tb $end
$scope module dut $end
$scope module datapath_inst $end
$scope module reg_file_inst $end
$var reg 128 +" \v_reg[1] [127:0] $end
$upscope $end
$upscope $end
$upscope $end
$upscope $end
$scope module simd_core_tb $end
$scope module dut $end
$scope module datapath_inst $end
$scope module reg_file_inst $end
$var reg 128 ," \v_reg[2] [127:0] $end
$upscope $end
$upscope $end
$upscope $end
$upscope $end
$scope module simd_core_tb $end
$scope module dut $end
$scope module datapath_inst $end
$scope module reg_file_inst $end
$var reg 128 -" \v_reg[3] [127:0] $end
$upscope $end
$upscope $end
$upscope $end
$upscope $end
$scope module simd_core_tb $end
$scope module dut $end
$scope module datapath_inst $end
$scope module reg_file_inst $end
$var reg 128 ." \v_reg[4] [127:0] $end
$upscope $end
$upscope $end
$upscope $end
$upscope $end
$scope module simd_core_tb $end
$scope module dut $end
$scope module datapath_inst $end
$scope module reg_file_inst $end
$var reg 128 /" \v_reg[5] [127:0] $end
$upscope $end
$upscope $end
$upscope $end
$upscope $end
$scope module simd_core_tb $end
$scope module dut $end
$scope module datapath_inst $end
$scope module reg_file_inst $end
$var reg 128 0" \v_reg[6] [127:0] $end
$upscope $end
$upscope $end
$upscope $end
$upscope $end
$scope module simd_core_tb $end
$scope module dut $end
$scope module datapath_inst $end
$scope module reg_file_inst $end
$var reg 128 1" \v_reg[7] [127:0] $end
$upscope $end
$upscope $end
$upscope $end
$upscope $end
$scope module simd_core_tb $end
$scope module dut $end
$scope module ram_inst $end
$var reg 128 2" \sram[0] [127:0] $end
$upscope $end
$upscope $end
$upscope $end
$scope module simd_core_tb $end
$scope module dut $end
$scope module ram_inst $end
$var reg 128 3" \sram[1] [127:0] $end
$upscope $end
$upscope $end
$upscope $end
$scope module simd_core_tb $end
$scope module dut $end
$scope module ram_inst $end
$var reg 128 4" \sram[2] [127:0] $end
$upscope $end
$upscope $end
$upscope $end
$enddefinitions $end
$comment Show the parameter values. $end
$dumpall
b10 y
b10001 x
b1000 w
b10000 v
b100 u
b1 t
b110000 s
b1 d
b11 c
b10 b
b0 a
b11 ]
b1 Z
b11 Y
b10 X
b0 W
b10 S
b1 P
b11 O
b10 N
b0 M
b1 I
b1 F
b11 E
b10 D
b0 C
b0 ?
$end
#0
$dumpvars
b0 4"
b101000000000000000000000000000001010000000000000000000000000000010100000000000000000000000000000101 3"
b101000000000000000000000000000000111100000000000000000000000000001010000000000000000000000000000001010 2"
bx 1"
bx 0"
bx /"
bx ."
bx -"
bx ,"
bx +"
bx *"
b1000 )"
b1000000 ("
b0 '"
bx &"
bx %"
b100000000 $"
b101000000000000000000000000000000111100000000000000000000000000001010000000000000000000000000000001010 #"
b0 ""
bx !"
b0 ~
bx }
b0 |
b0 {
b0 z
b0 r
b0 q
b0 p
b0 o
b0 n
b0 m
bx l
bx k
b0 j
b0 i
b0 h
bx g
bx f
xe
b0 `
bx _
bx ^
bx \
x[
b0 V
bx U
bx T
bx R
xQ
b0 L
bx K
bx J
bx H
xG
b0 B
bx A
bx @
bx >
b0 =
bx <
bx ;
bx :
bx 9
bx 8
b0 7
bx 6
b101000000000000000000000000000000111100000000000000000000000000001010000000000000000000000000000001010 5
b0 4
b0 3
b0 2
bx 1
b0 0
0/
0.
0-
b0 ,
b0 +
b0 *
0)
0(
bx '
b0 &
b0 %
b101000000000000000000000000000000111100000000000000000000000000001010000000000000000000000000000001010 $
bx #
1"
0!
$end
#5000
b101000000000000000000000000000000111100000000000000000000000000001010000000000000000000000000000001010 :
b101000000000000000000000000000000111100000000000000000000000000001010000000000000000000000000000001010 g
1)
1(
b1 ,
b1 4
b1 j
b1 o
b10000 p
b1000000100000000000000000000000 %
b1000000100000000000000000000000 q
b1000000100000000000000000000000 '"
b0 &"
b0 #
b0 }
b0 %"
1!
#10000
0!
#15000
b101000000000000000000000000000000111100000000000000000000000000001010000000000000000000000000000001010 +"
1!
#20000
0"
0!
#25000
b101000000000000000000000000000001010000000000000000000000000000010100000000000000000000000000000101 :
b101000000000000000000000000000001010000000000000000000000000000010100000000000000000000000000000101 g
b101000000000000000000000000000001010000000000000000000000000000010100000000000000000000000000000101 $
b101000000000000000000000000000001010000000000000000000000000000010100000000000000000000000000000101 5
b101000000000000000000000000000001010000000000000000000000000000010100000000000000000000000000000101 #"
b1 ""
b10000 |
b10000 ~
b10000 &
b10000 r
b10000 {
b10 ,
b10 4
b10 j
b10 o
b1000001000000000000000000010000 %
b1000001000000000000000000010000 q
b1000001000000000000000000010000 '"
b1 &"
b100 #
b100 }
b100 %"
b101000000000000000000000000000000111100000000000000000000000000001010000000000000000000000000000001010 +"
1!
#30000
0!
#35000
b101101 f
b100011 \
b11001 R
b101101000000000000000000000000001000110000000000000000000000000001100100000000000000000000000000001111 6
b101101000000000000000000000000001000110000000000000000000000000001100100000000000000000000000000001111 ;
b1111 H
b101000000000000000000000000000000111100000000000000000000000000001010000000000000000000000000000001010 $
b101000000000000000000000000000000111100000000000000000000000000001010000000000000000000000000000001010 5
b101000000000000000000000000000000111100000000000000000000000000001010000000000000000000000000000001010 #"
b101 _
b101 U
b101 K
b101 A
b101000 ^
b11110 T
b10100 J
b1010 @
b101101000000000000000000000000001000110000000000000000000000000001100100000000000000000000000000001111 :
b101101000000000000000000000000001000110000000000000000000000000001100100000000000000000000000000001111 g
b0 ""
b101000000000000000000000000000001010000000000000000000000000000010100000000000000000000000000000101 8
b101000000000000000000000000000001010000000000000000000000000000010100000000000000000000000000000101 <
b101000000000000000000000000000001010000000000000000000000000000010100000000000000000000000000000101 l
b101000000000000000000000000000000111100000000000000000000000000001010000000000000000000000000000001010 '
b101000000000000000000000000000000111100000000000000000000000000001010000000000000000000000000000001010 1
b101000000000000000000000000000000111100000000000000000000000000001010000000000000000000000000000001010 !"
b101000000000000000000000000000000111100000000000000000000000000001010000000000000000000000000000001010 9
b101000000000000000000000000000000111100000000000000000000000000001010000000000000000000000000000001010 >
b101000000000000000000000000000000111100000000000000000000000000001010000000000000000000000000000001010 k
0)
1(
b0 |
b0 ~
b0 &
b0 r
b0 {
b10 *
b10 2
b10 h
b10 m
b1 +
b1 3
b1 i
b1 n
b11 ,
b11 4
b11 j
b11 o
b1 p
b101100101000000000000000000 %
b101100101000000000000000000 q
b101100101000000000000000000 '"
b10 &"
b101000000000000000000000000000001010000000000000000000000000000010100000000000000000000000000000101 ,"
b1000 #
b1000 }
b1000 %"
1!
#40000
0!
#45000
bx :
bx g
bx f
bx \
bx R
bx 6
bx ;
bx H
b0 $
b0 5
b0 #"
bx _
bx U
bx K
bx A
b101101 ^
b100011 T
b11001 J
b1111 @
b10 ""
bx 8
bx <
bx l
b101101000000000000000000000000001000110000000000000000000000000001100100000000000000000000000000001111 '
b101101000000000000000000000000001000110000000000000000000000000001100100000000000000000000000000001111 1
b101101000000000000000000000000001000110000000000000000000000000001100100000000000000000000000000001111 !"
b101101000000000000000000000000001000110000000000000000000000000001100100000000000000000000000000001111 9
b101101000000000000000000000000001000110000000000000000000000000001100100000000000000000000000000001111 >
b101101000000000000000000000000001000110000000000000000000000000001100100000000000000000000000000001111 k
1-
0(
b100000 |
b100000 ~
b100000 &
b100000 r
b100000 {
b0 *
b0 2
b0 h
b0 m
b11 +
b11 3
b11 i
b11 n
b0 ,
b0 4
b0 j
b0 o
b10001 p
b1000100001100000000000000100000 %
b1000100001100000000000000100000 q
b1000100001100000000000000100000 '"
b11 &"
b1100 #
b1100 }
b1100 %"
b101101000000000000000000000000001000110000000000000000000000000001100100000000000000000000000000001111 -"
1!
#50000
0!
#55000
1.
b0 f
b0 \
b0 R
b0 6
b0 ;
b0 H
b101000 _
b11110 U
b10100 K
b1010 A
b101000 ^
b11110 T
b10100 J
b1010 @
b101000000000000000000000000000000111100000000000000000000000000001010000000000000000000000000000001010 :
b101000000000000000000000000000000111100000000000000000000000000001010000000000000000000000000000001010 g
b0 ""
b101000000000000000000000000000000111100000000000000000000000000001010000000000000000000000000000001010 8
b101000000000000000000000000000000111100000000000000000000000000001010000000000000000000000000000001010 <
b101000000000000000000000000000000111100000000000000000000000000001010000000000000000000000000000001010 l
b101000000000000000000000000000000111100000000000000000000000000001010000000000000000000000000000001010 '
b101000000000000000000000000000000111100000000000000000000000000001010000000000000000000000000000001010 1
b101000000000000000000000000000000111100000000000000000000000000001010000000000000000000000000000001010 !"
b101000000000000000000000000000000111100000000000000000000000000001010000000000000000000000000000001010 9
b101000000000000000000000000000000111100000000000000000000000000001010000000000000000000000000000001010 >
b101000000000000000000000000000000111100000000000000000000000000001010000000000000000000000000000001010 k
1/
b1 0
b1 7
b1 =
b1 B
b1 L
b1 V
b1 `
b1 z
1)
0-
b0 |
b0 ~
b0 &
b0 r
b0 {
b1 *
b1 2
b1 h
b1 m
b1 +
b1 3
b1 i
b1 n
b110000 p
b11000000000100100000000000000000 %
b11000000000100100000000000000000 q
b11000000000100100000000000000000 '"
b101000000000000000000000000000000111100000000000000000000000000001010000000000000000000000000000001010 $
b101000000000000000000000000000000111100000000000000000000000000001010000000000000000000000000000001010 5
b101000000000000000000000000000000111100000000000000000000000000001010000000000000000000000000000001010 #"
b100 &"
b101101000000000000000000000000001000110000000000000000000000000001100100000000000000000000000000001111 4"
b10000 #
b10000 }
b10000 %"
1!
