rtl/alu.sv
`default_nettype none

module alu (
    input  wire  [31:0] a,
    input  wire  [31:0] b,
    input  wire  [ 1:0] alu_op,
    output logic [31:0] result,
    output logic        is_zero
);

  localparam logic [1:0] OP_ADD = 2'b00;
  localparam logic [1:0] OP_SUB = 2'b01;
  localparam logic [1:0] OP_AND = 2'b10;
  localparam logic [1:0] OP_OR  = 2'b11;

  always_comb begin
    case (alu_op)
      OP_ADD:  result = a + b;
      OP_SUB:  result = a - b;
      OP_AND:  result = a & b;
      OP_OR:   result = a | b;
      default: result = 32'd0;

    endcase
  end


endmodule

rtl/vector_alu.sv
`default_nettype none

module vector_alu (
    input  wire  [3:0][31:0] a,
    input  wire  [3:0][31:0] b,
    input  wire  [1:0]       alu_op,
    output logic [3:0][31:0] result,
    output logic             is_zero
);

  genvar i;
  generate
    for (i = 0; i < 4; i = i + 1) begin : g_alu_lanes
      alu alu_inst (
          .a(a[i]),
          .b(b[i]),
          .alu_op(alu_op),
          .result(result[i])
      );
    end
  endgenerate

  always_comb begin
    if (result == 128'd0) begin
      is_zero = 1'b1;
    end else begin
      is_zero = 1'b0;
    end
  end
endmodule

rtl/vector_regfile.sv
`default_nettype none

module vector_regfile (
    input wire             clk,
    input wire             we,
    input wire [2:0]       rs1,
    input wire [2:0]       rs2,
    input wire [2:0]       rd,
    input wire [3:0][31:0] wd,

    output logic [3:0][31:0] rd1_data,
    output logic [3:0][31:0] rd2_data
);

  logic [3:0][31:0] v_reg[8];

  always_ff @(posedge clk) begin
    if (we) begin
      v_reg[rd] <= wd;
    end
  end

  always_comb begin
    rd1_data = v_reg[rs1];
    rd2_data = v_reg[rs2];
  end

endmodule

rtl/simd_datapath.sv
`default_nettype none

module simd_datapath (
    input wire       clk,
    input wire       we,
    input wire [2:0] rs1,
    input wire [2:0] rs2,
    input wire [2:0] rd,
    input wire [1:0] alu_op,

    input  wire              wb_sel,
    input  wire  [3:0][31:0] ext_data_in,
    output logic             is_zero
);

  logic [3:0][31:0] alu_in_a;
  logic [3:0][31:0] alu_in_b;
  logic [3:0][31:0] alu_out;

  logic [3:0][31:0] write_back_data;

  always_comb begin
    if (wb_sel) begin
      write_back_data = ext_data_in;
    end else begin
      write_back_data = alu_out;
    end
  end

  vector_regfile reg_file_inst (
      .clk(clk),
      .we(we),
      .rs1(rs1),
      .rs2(rs2),
      .rd(rd),
      .wd(write_back_data),
      .rd1_data(alu_in_a),
      .rd2_data(alu_in_b)
  );

  vector_alu alu_inst (
      .a(alu_in_a),
      .b(alu_in_b),
      .alu_op(alu_op),
      .result(alu_out),
      .is_zero(is_zero)
  );

endmodule

rtl/instruction_decoder.sv
`default_nettype none

module instruction_decoder (
    input wire [31:0] instr,

    output logic        we,
    output logic [ 2:0] rs1,
    output logic [ 2:0] rs2,
    output logic [ 2:0] rd,
    output logic [ 2:0] alu_op,
    output logic        wb_sel,
    output logic        branch,
    output logic [16:0] imm
);

  localparam logic [5:0] OPC_VADD  = 6'b000001;
  localparam logic [5:0] OPC_VSUB  = 6'b000010;
  localparam logic [5:0] OPC_VAND  = 6'b000100;
  localparam logic [5:0] OPC_VOR   = 6'b001000;
  localparam logic [5:0] OPC_VLOAD = 6'b010000;
  localparam logic [5:0] OPC_BEQ   = 6'b110000;

  logic [5:0] opcode;

  assign opcode = instr[31:26];
  assign rd     = instr[25:23];
  assign rs1    = instr[22:20];
  assign rs2    = instr[19:17];
  assign imm    = instr[16:0];

  always_comb begin
    we     = 1'b0;
    wb_sel = 1'b0;
    alu_op = 2'b00;

    case (opcode)
      OPC_VADD: begin
        we     = 1'b1;
        wb_sel = 1'b0;
        alu_op = 2'b00;
      end
      OPC_VSUB: begin
        we     = 1'b1;
        wb_sel = 1'b0;
        alu_op = 2'b01;
      end
      OPC_VAND: begin
        we     = 1'b1;
        wb_sel = 1'b0;
        alu_op = 2'b10;
      end
      OPC_VOR: begin
        we     = 1'b1;
        wb_sel = 1'b0;
        alu_op = 2'b11;
      end
      OPC_VLOAD: begin
        we     = 1'b1;
        wb_sel = 1'b1;
        alu_op = 2'b00;
      end
      OPC_BEQ: begin
        we     = 1'b0;
        wb_sel = 1'b1;
        alu_op = 2'b01;
        branch = 1'b1;
      end

      default: begin
        we = 1'b0;
      end
    endcase
  end

endmodule

rtl/instruction_memory.sv
`default_nettype none

module instruction_memory (
    input  wire  [31:0] addr,
    output logic [31:0] instr
);

  logic [31:0] rom[64];

  initial begin
    // [0] PC = 0: VLOAD V1, Addr 0
    rom[0] = {6'b010000, 3'd1, 3'd0, 3'd0, 17'd0};

    // [1] PC = 4: VLOAD V2, Addr 16
    rom[1] = {6'b010000, 3'd2, 3'd0, 3'd0, 17'd16};

    // [2] PC = 8: VADD V3, V1, V2
    rom[2] = {6'b000001, 3'd3, 3'd1, 3'd2, 17'd0};

    // [3] PC = 12: VSTR V3, Addr 32 (Source data is in rs1)
    rom[3] = {6'b010001, 3'd0, 3'd3, 3'd0, 17'd32};

    // [4] PC = 16: BEQ V1, V1, +0 (Infinite loop / Halt)
    rom[4] = {6'b110000, 3'd0, 3'd1, 3'd1, 17'd0};

    // Pad remaining slots
    for (int i = 5; i < 64; i++) begin
      rom[i] = 32'h0000_0000;
    end
  end

  always_comb begin
    logic [29:0] word_index;
    word_index = addr[31:2];
    if (word_index < 64) begin
      instr = rom[word_index];
    end else begin
      instr = 32'h0000_0000;
    end
  end

endmodule

rtl/program_counter.sv
`default_nettype none

module program_counter (
    input wire clk,
    input wire reset,

    input wire        branch,
    input wire [16:0] imm,
    input wire        is_zero,

    output logic [31:0] pc
);

  logic [31:0] extended_imm;
  assign extended_imm = {{15{imm[16]}}, imm};

  always_ff @(posedge clk) begin
    if (reset) begin
      pc <= 32'd0;
    end else begin
      if (branch && is_zero) begin
        pc <= pc + extended_imm;
      end else begin
        pc <= pc + 32'd4;
      end
    end
  end

endmodule

rtl/simd_core.sv
`default_nettype none

module simd_core (
    input wire             clk,
    input wire             reset,
    input wire [3:0][31:0] ext_data_in
);

  logic        ctrl_we;
  logic [ 2:0] ctrl_rs1;
  logic [ 2:0] ctrl_rs2;
  logic [ 2:0] ctrl_rd;
  logic [ 2:0] ctrl_alu_op;
  logic        ctrl_wb_sel;

  logic        ctrl_is_zero;
  logic        ctrl_branch;

  logic [31:0] pc;
  logic [31:0] instr;
  logic [16:0] imm;


  program_counter pc_inst (
      .clk(clk),
      .reset(reset),
      .pc(pc),
      .branch(ctrl_branch),
      .imm(imm),
      .is_zero(ctrl_is_zero)
  );

  instruction_memory rom_inst (
      .addr (pc),
      .instr(instr)
  );

  instruction_decoder id_inst (
      .instr(instr),
      .we(ctrl_we),
      .rs1(ctrl_rs1),
      .rs2(ctrl_rs2),
      .rd(ctrl_rd),
      .alu_op(ctrl_alu_op),
      .wb_sel(ctrl_wb_sel),
      .branch(ctrl_branch),
      .imm(imm)
  );

  simd_datapath datapath_inst (
      .clk(clk),
      .we(ctrl_we),
      .rs1(ctrl_rs1),
      .rs2(ctrl_rs2),
      .rd(ctrl_rd),
      .alu_op(ctrl_alu_op),
      .wb_sel(ctrl_wb_sel),
      .ext_data_in(ext_data_in),
      .is_zero(ctrl_is_zero)
  );

endmodule

tb/simd_core_tb.sv
`default_nettype none
`timescale 1ns / 1ps

module simd_core_tb;

  // 1. Declare Signals
  logic             clk;
  logic             reset;
  logic [3:0][31:0] ext_data_in;

  // 2. Instantiate the CPU
  simd_core dut (.*);

  // 3. Clock Generation (100 MHz)
  initial begin
    clk = 0;
    forever #5 clk = ~clk;
  end

  // 4. The Boot Sequence
  initial begin
    $dumpfile("sim/simd_core.vcd");
    $dumpvars(0, simd_core_tb);

    // Dump internal registers so we can see them in GTKWave
    for (int k = 0; k < 8; k++) begin
      $dumpvars(0, dut.datapath_inst.reg_file_inst.v_reg[k]);
    end

    // --- PHASE 1: SYSTEM RESET ---
    // Turn the reset line ON to clear the Program Counter
    reset       = 1'b1;
    ext_data_in = '0;

    // Hold reset for 20ns to let the silicon stabilize
    #20;

    // --- PHASE 2: BOOT UP ---
    // Release reset on the negative edge. The CPU wakes up and starts fetching!
    @(negedge clk);
    reset          = 1'b0;

    // Cycle 1: PC is 0. ROM outputs VLOAD V1. 
    // We feed the external bus with the data it expects to load.
    ext_data_in[0] = 32'd10;
    ext_data_in[1] = 32'd20;
    ext_data_in[2] = 32'd30;
    ext_data_in[3] = 32'd40;

    // Cycle 2: PC is 4. ROM outputs VLOAD V2.
    // Change the external data bus for the next load.
    @(negedge clk);
    ext_data_in[0] = 32'd5;
    ext_data_in[1] = 32'd5;
    ext_data_in[2] = 32'd5;
    ext_data_in[3] = 32'd5;

    // Cycle 3: PC is 8. ROM outputs VADD V3, V1, V2.
    // Cycle 4: PC is 12. ROM outputs VSUB V4, V3, V2.
    // Since the CPU is doing math, it ignores ext_data_in. We just let it run.
    #50;

    // --- PHASE 3: VERIFY ---
    $display("\n--- AUTONOMOUS EXECUTION COMPLETE ---");
    $display("V1 (Loaded) : %0d, %0d, %0d, %0d", dut.datapath_inst.reg_file_inst.v_reg[1][0],
             dut.datapath_inst.reg_file_inst.v_reg[1][1],
             dut.datapath_inst.reg_file_inst.v_reg[1][2],
             dut.datapath_inst.reg_file_inst.v_reg[1][3]);

    $display("V3 (V1 + V2): %0d, %0d, %0d, %0d", dut.datapath_inst.reg_file_inst.v_reg[3][0],
             dut.datapath_inst.reg_file_inst.v_reg[3][1],
             dut.datapath_inst.reg_file_inst.v_reg[3][2],
             dut.datapath_inst.reg_file_inst.v_reg[3][3]);

    $display("V4 (V3 - V2): %0d, %0d, %0d, %0d", dut.datapath_inst.reg_file_inst.v_reg[4][0],
             dut.datapath_inst.reg_file_inst.v_reg[4][1],
             dut.datapath_inst.reg_file_inst.v_reg[4][2],
             dut.datapath_inst.reg_file_inst.v_reg[4][3]);

    $finish;
  end

endmodule

sim/simd_core.vcd
$date
	Sun Sep  6 00:43:13 2026
$end
$version
	Icarus Verilog
$end
$timescale
	1ps
$end
$scope module simd_core_tb $end
$var reg 1 ! clk $end
$var reg 128 " ext_data_in [127:0] $end
$var reg 1 # reset $end
$scope module dut $end
$var wire 1 ! clk $end
$var wire 128 $ ext_data_in [127:0] $end
$var wire 1 # reset $end
$var wire 32 % pc [31:0] $end
$var wire 32 & instr [31:0] $end
$var wire 17 ' imm [16:0] $end
$var wire 1 ( ctrl_we $end
$var wire 1 ) ctrl_wb_sel $end
$var wire 3 * ctrl_rs2 [2:0] $end
$var wire 3 + ctrl_rs1 [2:0] $end
$var wire 3 , ctrl_rd [2:0] $end
$var wire 1 - ctrl_is_zero $end
$var wire 1 . ctrl_branch $end
$var wire 3 / ctrl_alu_op [2:0] $end
$scope module datapath_inst $end
$var wire 2 0 alu_op [1:0] $end
$var wire 1 ! clk $end
$var wire 128 1 ext_data_in [127:0] $end
$var wire 1 ( we $end
$var wire 1 ) wb_sel $end
$var wire 3 2 rs2 [2:0] $end
$var wire 3 3 rs1 [2:0] $end
$var wire 3 4 rd [2:0] $end
$var wire 1 - is_zero $end
$var wire 128 5 alu_out [127:0] $end
$var wire 128 6 alu_in_b [127:0] $end
$var wire 128 7 alu_in_a [127:0] $end
$var reg 128 8 write_back_data [127:0] $end
$scope module alu_inst $end
$var wire 2 9 alu_op [1:0] $end
$var wire 128 : result [127:0] $end
$var wire 128 ; b [127:0] $end
$var wire 128 < a [127:0] $end
$var reg 1 - is_zero $end
$scope begin g_alu_lanes[0] $end
$var parameter 2 = i $end
$scope module alu_inst $end
$var wire 32 > a [31:0] $end
$var wire 2 ? alu_op [1:0] $end
$var wire 32 @ b [31:0] $end
$var parameter 2 A OP_ADD $end
$var parameter 2 B OP_AND $end
$var parameter 2 C OP_OR $end
$var parameter 2 D OP_SUB $end
$var reg 1 E is_zero $end
$var reg 32 F result [31:0] $end
$upscope $end
$upscope $end
$scope begin g_alu_lanes[1] $end
$var parameter 2 G i $end
$scope module alu_inst $end
$var wire 32 H a [31:0] $end
$var wire 2 I alu_op [1:0] $end
$var wire 32 J b [31:0] $end
$var parameter 2 K OP_ADD $end
$var parameter 2 L OP_AND $end
$var parameter 2 M OP_OR $end
$var parameter 2 N OP_SUB $end
$var reg 1 O is_zero $end
$var reg 32 P result [31:0] $end
$upscope $end
$upscope $end
$scope begin g_alu_lanes[2] $end
$var parameter 3 Q i $end
$scope module alu_inst $end
$var wire 32 R a [31:0] $end
$var wire 2 S alu_op [1:0] $end
$var wire 32 T b [31:0] $end
$var parameter 2 U OP_ADD $end
$var parameter 2 V OP_AND $end
$var parameter 2 W OP_OR $end
$var parameter 2 X OP_SUB $end
$var reg 1 Y is_zero $end
$var reg 32 Z result [31:0] $end
$upscope $end
$upscope $end
$scope begin g_alu_lanes[3] $end
$var parameter 3 [ i $end
$scope module alu_inst $end
$var wire 32 \ a [31:0] $end
$var wire 2 ] alu_op [1:0] $end
$var wire 32 ^ b [31:0] $end
$var parameter 2 _ OP_ADD $end
$var parameter 2 ` OP_AND $end
$var parameter 2 a OP_OR $end
$var parameter 2 b OP_SUB $end
$var reg 1 c is_zero $end
$var reg 32 d result [31:0] $end
$upscope $end
$upscope $end
$upscope $end
$scope module reg_file_inst $end
$var wire 1 ! clk $end
$var wire 128 e wd [127:0] $end
$var wire 1 ( we $end
$var wire 3 f rs2 [2:0] $end
$var wire 3 g rs1 [2:0] $end
$var wire 3 h rd [2:0] $end
$var reg 128 i rd1_data [127:0] $end
$var reg 128 j rd2_data [127:0] $end
$upscope $end
$upscope $end
$scope module id_inst $end
$var wire 3 k rs2 [2:0] $end
$var wire 3 l rs1 [2:0] $end
$var wire 3 m rd [2:0] $end
$var wire 6 n opcode [5:0] $end
$var wire 32 o instr [31:0] $end
$var wire 17 p imm [16:0] $end
$var parameter 6 q OPC_BEQ $end
$var parameter 6 r OPC_VADD $end
$var parameter 6 s OPC_VAND $end
$var parameter 6 t OPC_VLOAD $end
$var parameter 6 u OPC_VOR $end
$var parameter 6 v OPC_VSUB $end
$var reg 3 w alu_op [2:0] $end
$var reg 1 . branch $end
$var reg 1 ) wb_sel $end
$var reg 1 ( we $end
$upscope $end
$scope module pc_inst $end
$var wire 1 . branch $end
$var wire 1 ! clk $end
$var wire 17 x imm [16:0] $end
$var wire 1 - is_zero $end
$var wire 1 # reset $end
$var wire 32 y extended_imm [31:0] $end
$var reg 32 z pc [31:0] $end
$upscope $end
$scope module rom_inst $end
$var wire 32 { addr [31:0] $end
$var reg 32 | instr [31:0] $end
$scope begin $ivl_for_loop0 $end
$var integer 32 } i [31:0] $end
$upscope $end
$scope begin $unm_blk_12 $end
$var reg 30 ~ word_index [29:0] $end
$upscope $end
$upscope $end
$upscope $end
$scope begin $ivl_for_loop1 $end
$var integer 32 !" k [31:0] $end
$upscope $end
$upscope $end
$scope module simd_core_tb $end
$scope module dut $end
$scope module datapath_inst $end
$scope module reg_file_inst $end
$var reg 128 "" \v_reg[0] [127:0] $end
$upscope $end
$upscope $end
$upscope $end
$upscope $end
$scope module simd_core_tb $end
$scope module dut $end
$scope module datapath_inst $end
$scope module reg_file_inst $end
$var reg 128 #" \v_reg[1] [127:0] $end
$upscope $end
$upscope $end
$upscope $end
$upscope $end
$scope module simd_core_tb $end
$scope module dut $end
$scope module datapath_inst $end
$scope module reg_file_inst $end
$var reg 128 $" \v_reg[2] [127:0] $end
$upscope $end
$upscope $end
$upscope $end
$upscope $end
$scope module simd_core_tb $end
$scope module dut $end
$scope module datapath_inst $end
$scope module reg_file_inst $end
$var reg 128 %" \v_reg[3] [127:0] $end
$upscope $end
$upscope $end
$upscope $end
$upscope $end
$scope module simd_core_tb $end
$scope module dut $end
$scope module datapath_inst $end
$scope module reg_file_inst $end
$var reg 128 &" \v_reg[4] [127:0] $end
$upscope $end
$upscope $end
$upscope $end
$upscope $end
$scope module simd_core_tb $end
$scope module dut $end
$scope module datapath_inst $end
$scope module reg_file_inst $end
$var reg 128 '" \v_reg[5] [127:0] $end
$upscope $end
$upscope $end
$upscope $end
$upscope $end
$scope module simd_core_tb $end
$scope module dut $end
$scope module datapath_inst $end
$scope module reg_file_inst $end
$var reg 128 (" \v_reg[6] [127:0] $end
$upscope $end
$upscope $end
$upscope $end
$upscope $end
$scope module simd_core_tb $end
$scope module dut $end
$scope module datapath_inst $end
$scope module reg_file_inst $end
$var reg 128 )" \v_reg[7] [127:0] $end
$upscope $end
$upscope $end
$upscope $end
$upscope $end
$enddefinitions $end
$comment Show the parameter values. $end
$dumpall
b10 v
b1000 u
b10000 t
b100 s
b1 r
b110000 q
b1 b
b11 a
b10 `
b0 _
b11 [
b1 X
b11 W
b10 V
b0 U
b10 Q
b1 N
b11 M
b10 L
b0 K
b1 G
b1 D
b11 C
b10 B
b0 A
b0 =
$end
#0
$dumpvars
bx )"
bx ("
bx '"
bx &"
bx %"
bx $"
bx #"
bx ""
b1000 !"
bx ~
b1000000 }
b0 |
bx {
bx z
b0 y
b0 x
b0 w
b0 p
b0 o
b0 n
b0 m
b0 l
b0 k
bx j
bx i
b0 h
b0 g
b0 f
bx e
bx d
xc
bx ^
b0 ]
bx \
bx Z
xY
bx T
b0 S
bx R
bx P
xO
bx J
b0 I
bx H
bx F
xE
bx @
b0 ?
bx >
bx <
bx ;
bx :
b0 9
bx 8
bx 7
bx 6
bx 5
b0 4
b0 3
b0 2
b0 1
b0 0
b0 /
0.
0-
b0 ,
b0 +
b0 *
0)
0(
b0 '
b0 &
bx %
b0 $
1#
b0 "
0!
$end
#5000
b0 8
b0 e
1)
1(
b1 ,
b1 4
b1 h
b1 m
b10000 n
b1000000100000000000000000000000 &
b1000000100000000000000000000000 o
b1000000100000000000000000000000 |
b0 ~
b0 %
b0 z
b0 {
1!
#10000
0!
#15000
b0 #"
1!
#20000
b101000000000000000000000000000000111100000000000000000000000000001010000000000000000000000000000001010 8
b101000000000000000000000000000000111100000000000000000000000000001010000000000000000000000000000001010 e
b101000000000000000000000000000000111100000000000000000000000000001010000000000000000000000000000001010 "
b101000000000000000000000000000000111100000000000000000000000000001010000000000000000000000000000001010 $
b101000000000000000000000000000000111100000000000000000000000000001010000000000000000000000000000001010 1
0#
0!
#25000
b10 ,
b10 4
b10 h
b10 m
b1000001000000000000000000000000 &
b1000001000000000000000000000000 o
b1000001000000000000000000000000 |
b1 ~
b100 %
b100 z
b100 {
b101000000000000000000000000000000111100000000000000000000000000001010000000000000000000000000000001010 #"
1!
#30000
0!
#35000
1-
b0 F
b0 P
b0 Z
b0 5
b0 :
b0 d
b101000 ^
b11110 T
b10100 J
b1010 @
b101000 \
b11110 R
b10100 H
b1010 >
b1 0
b1 9
b1 ?
b1 I
b1 S
b1 ]
b101000000000000000000000000000000111100000000000000000000000000001010000000000000000000000000000001010 6
b101000000000000000000000000000000111100000000000000000000000000001010000000000000000000000000000001010 ;
b101000000000000000000000000000000111100000000000000000000000000001010000000000000000000000000000001010 j
b101000000000000000000000000000000111100000000000000000000000000001010000000000000000000000000000001010 7
b101000000000000000000000000000000111100000000000000000000000000001010000000000000000000000000000001010 <
b101000000000000000000000000000000111100000000000000000000000000001010000000000000000000000000000001010 i
1.
b1 /
b1 w
1)
0(
b1100 y
b1100 '
b1100 p
b1100 x
b10 *
b10 2
b10 f
b10 k
b1 +
b1 3
b1 g
b1 l
b0 ,
b0 4
b0 h
b0 m
b110000 n
b11000000000101000000000000001100 &
b11000000000101000000000000001100 o
b11000000000101000000000000001100 |
b10 ~
b101000000000000000000000000000000111100000000000000000000000000001010000000000000000000000000000001010 $"
b1000 %
b1000 z
b1000 {
1!
#40000
b0 8
b0 e
b0 "
b0 $
b0 1
0!
#45000
1(
0.
b1 /
b1 w
0)
b0 y
b0 '
b0 p
b0 x
b100 ,
b100 4
b100 h
b100 m
b10 n
b1010000101000000000000000000 &
b1010000101000000000000000000 o
b1010000101000000000000000000 |
b101 ~
b10100 %
b10100 z
b10100 {
1!
#50000
0!
#55000
bx 8
bx e
0-
bx F
bx P
bx Z
bx 5
bx :
bx d
bx ^
bx T
bx J
bx @
bx \
bx R
bx H
bx >
b0 0
b0 9
b0 ?
b0 I
b0 S
b0 ]
bx 6
bx ;
bx j
bx 7
bx <
bx i
b0 /
b0 w
0(
b0 *
b0 2
b0 f
b0 k
b0 +
b0 3
b0 g
b0 l
b0 ,
b0 4
b0 h
b0 m
b0 n
b0 &
b0 o
b0 |
b110 ~
b0 &"
b11000 %
b11000 z
b11000 {
1!
#60000
0!
#65000
b111 ~
b11100 %
b11100 z
b11100 {
1!
#70000
0!
#75000
b1000 ~
b100000 %
b100000 z
b100000 {
1!
#80000
1#
0!
#85000
b0 8
b0 e
1)
1(
b1 ,
b1 4
b1 h
b1 m
b10000 n
b1000000100000000000000000000000 &
b1000000100000000000000000000000 o
b1000000100000000000000000000000 |
b0 ~
b0 %
b0 z
b0 {
1!
#90000
0!
#95000
b0 #"
1!
#100000
b101000000000000000000000000000000111100000000000000000000000000001010000000000000000000000000000001010 8
b101000000000000000000000000000000111100000000000000000000000000001010000000000000000000000000000001010 e
b101000000000000000000000000000000111100000000000000000000000000001010000000000000000000000000000001010 "
b101000000000000000000000000000000111100000000000000000000000000001010000000000000000000000000000001010 $
b101000000000000000000000000000000111100000000000000000000000000001010000000000000000000000000000001010 1
0#
0!
#105000
b10 ,
b10 4
b10 h
b10 m
b1000001000000000000000000000000 &
b1000001000000000000000000000000 o
b1000001000000000000000000000000 |
b1 ~
b100 %
b100 z
b100 {
b101000000000000000000000000000000111100000000000000000000000000001010000000000000000000000000000001010 #"
1!
#110000
b101000000000000000000000000000001010000000000000000000000000000010100000000000000000000000000000101 8
b101000000000000000000000000000001010000000000000000000000000000010100000000000000000000000000000101 e
b101000000000000000000000000000001010000000000000000000000000000010100000000000000000000000000000101 "
b101000000000000000000000000000001010000000000000000000000000000010100000000000000000000000000000101 $
b101000000000000000000000000000001010000000000000000000000000000010100000000000000000000000000000101 1
0!
#115000
b101 F
b1111 P
b11001 Z
b100011000000000000000000000000000110010000000000000000000000000000111100000000000000000000000000000101 5
b100011000000000000000000000000000110010000000000000000000000000000111100000000000000000000000000000101 :
b100011 d
b101 ^
b101 T
b101 J
b101 @
b101000 \
b11110 R
b10100 H
b1010 >
b1 0
b1 9
b1 ?
b1 I
b1 S
b1 ]
b101000000000000000000000000000001010000000000000000000000000000010100000000000000000000000000000101 6
b101000000000000000000000000000001010000000000000000000000000000010100000000000000000000000000000101 ;
b101000000000000000000000000000001010000000000000000000000000000010100000000000000000000000000000101 j
b101000000000000000000000000000000111100000000000000000000000000001010000000000000000000000000000001010 7
b101000000000000000000000000000000111100000000000000000000000000001010000000000000000000000000000001010 <
b101000000000000000000000000000000111100000000000000000000000000001010000000000000000000000000000001010 i
1.
b1 /
b1 w
1)
0(
b1100 y
b1100 '
b1100 p
b1100 x
b10 *
b10 2
b10 f
b10 k
b1 +
b1 3
b1 g
b1 l
b0 ,
b0 4
b0 h
b0 m
b110000 n
b11000000000101000000000000001100 &
b11000000000101000000000000001100 o
b11000000000101000000000000001100 |
b10 ~
b101000000000000000000000000000001010000000000000000000000000000010100000000000000000000000000000101 $"
b1000 %
b1000 z
b1000 {
1!
#120000
b0 8
b0 e
b0 "
b0 $
b0 1
0!
#125000
b1111 F
b11001 P
b100011 Z
b101101000000000000000000000000001000110000000000000000000000000001100100000000000000000000000000001111 5
b101101000000000000000000000000001000110000000000000000000000000001100100000000000000000000000000001111 :
b101101 d
b0 0
b0 9
b0 ?
b0 I
b0 S
b0 ]
b101101000000000000000000000000001000110000000000000000000000000001100100000000000000000000000000001111 8
b101101000000000000000000000000001000110000000000000000000000000001100100000000000000000000000000001111 e
1(
0.
b0 /
b0 w
0)
b0 y
b0 '
b0 p
b0 x
b11 ,
b11 4
b11 h
b11 m
b1 n
b101100101000000000000000000 &
b101100101000000000000000000 o
b101100101000000000000000000 |
b11 ~
b1100 %
b1100 z
b1100 {
1!
#130000
0!
#135000
bx 8
bx e
bx d
bx Z
bx P
bx 5
bx :
bx F
bx ^
bx T
bx J
bx @
bx \
bx R
bx H
bx >
bx 6
bx ;
bx j
bx 7
bx <
bx i
0(
b0 *
b0 2
b0 f
b0 k
b0 +
b0 3
b0 g
b0 l
b0 ,
b0 4
b0 h
b0 m
b0 n
b0 &
b0 o
b0 |
b100 ~
b101101000000000000000000000000001000110000000000000000000000000001100100000000000000000000000000001111 %"
b10000 %
b10000 z
b10000 {
1!
#140000
0!
#145000
b100011000000000000000000000000000110010000000000000000000000000000111100000000000000000000000000000101 8
b100011000000000000000000000000000110010000000000000000000000000000111100000000000000000000000000000101 e
b101 F
b1111 P
b11001 Z
b100011000000000000000000000000000110010000000000000000000000000000111100000000000000000000000000000101 5
b100011000000000000000000000000000110010000000000000000000000000000111100000000000000000000000000000101 :
b100011 d
b101 ^
b101 T
b101 J
b101 @
b101000 \
b11110 R
b10100 H
b1010 >
b1 0
b1 9
b1 ?
b1 I
b1 S
b1 ]
b101000000000000000000000000000001010000000000000000000000000000010100000000000000000000000000000101 6
b101000000000000000000000000000001010000000000000000000000000000010100000000000000000000000000000101 ;
b101000000000000000000000000000001010000000000000000000000000000010100000000000000000000000000000101 j
b101000000000000000000000000000000111100000000000000000000000000001010000000000000000000000000000001010 7
b101000000000000000000000000000000111100000000000000000000000000001010000000000000000000000000000001010 <
b101000000000000000000000000000000111100000000000000000000000000001010000000000000000000000000000001010 i
b1 /
b1 w
1(
b10 *
b10 2
b10 f
b10 k
b1 +
b1 3
b1 g
b1 l
b100 ,
b100 4
b100 h
b100 m
b10 n
b1010000101000000000000000000 &
b1010000101000000000000000000 o
b1010000101000000000000000000 |
b101 ~
b10100 %
b10100 z
b10100 {
1!
#150000
0!
#155000
bx 8
bx e
bx F
bx P
bx Z
bx 5
bx :
bx d
bx ^
bx T
bx J
bx @
bx \
bx R
bx H
bx >
b0 0
b0 9
b0 ?
b0 I
b0 S
b0 ]
bx 6
bx ;
bx j
bx 7
bx <
bx i
b0 /
b0 w
0(
b0 *
b0 2
b0 f
b0 k
b0 +
b0 3
b0 g
b0 l
b0 ,
b0 4
b0 h
b0 m
b0 n
b0 &
b0 o
b0 |
b110 ~
b100011000000000000000000000000000110010000000000000000000000000000111100000000000000000000000000000101 &"
b11000 %
b11000 z
b11000 {
1!
