rtl/alu.sv
`default_nettype none

module alu (
    input  wire  [31:0] a,
    input  wire  [31:0] b,
    input  wire  [ 1:0] alu_op,
    output logic [31:0] result
);

  localparam logic [1:0] OP_ADD = 2'b00;
  localparam logic [1:0] OP_SUB = 2'b01;
  localparam logic [1:0] OP_AND = 2'b10;
  localparam logic [1:0] OP_OR  = 2'b11;

  always_comb begin
    case (alu_op)
      OP_ADD:  result = a + b;
      OP_SUB:  result = a - b;
      OP_AND:  result = a & b;
      OP_OR:   result = a | b;
      default: result = 32'd0;
    endcase
  end

endmodule

rtl/vector_alu.sv
`default_nettype none

module vector_alu (
    input  wire  [3:0][31:0] a,
    input  wire  [3:0][31:0] b,
    input  wire  [1:0]       alu_op,
    output logic [3:0][31:0] result
);

  genvar i;
  generate
    for (i = 0; i < 4; i = i + 1) begin : g_alu_lanes
      alu alu_inst (
          .a(a[i]),
          .b(b[i]),
          .alu_op(alu_op),
          .result(result[i])
      );
    end
  endgenerate

endmodule

tb/vector_alu_tb.sv
`timescale 1ns / 1ps

module vector_alu_tb;
  logic [3:0][31:0] a;
  logic [3:0][31:0] b;
  logic [1:0]       alu_op;
  logic [3:0][31:0] result;

  vector_alu dut (.*);

  initial begin
    int i, j;
    int          error_count = 0;
    logic [31:0] expected;

    $dumpfile("sim/vector_alu.vcd");
    $dumpvars(0, vector_alu_tb);

    error_count = 0;
    a           = 0;
    b           = 0;
    alu_op      = 0;

    #10;

    $display("Start loop test");

    for (i = 0; i < 100; i++) begin
      for (j = 0; j < 4; j++) begin
        a[j] = $urandom();
        b[j] = $urandom();
      end

      alu_op = $urandom_range(0, 3);
      #1;

      for (j = 0; j < 4; j++) begin
        case (alu_op)
          2'b00:   expected = a[j] + b[j];
          2'b01:   expected = a[j] - b[j];
          2'b10:   expected = a[j] & b[j];
          2'b11:   expected = a[j] | b[j];
          default: expected = 0;
        endcase

        if (result[j] !== expected) begin
          $error("FAIL: vector %0d, lane %0d, op %0d: expected %0h (Hardware returned %0h)", i, j,
                 alu_op, expected, result[j]);
          error_count++;
        end
      end

      #9;
    end


    if (error_count == 0) $display("SUCCESS: 400 parallel ALU operations verified!");
    else $display("FAILED with %0d errors.", error_count);

    $finish;
  end

endmodule

sim/vector_alu.vcd
$date
	Thu Sep  3 01:38:39 2026
$end
$version
	Icarus Verilog
$end
$timescale
	1ps
$end
$scope module vector_alu_tb $end
$var wire 128 ! result [127:0] $end
$var reg 128 " a [127:0] $end
$var reg 2 # alu_op [1:0] $end
$var reg 128 $ b [127:0] $end
$scope module dut $end
$var wire 128 % a [127:0] $end
$var wire 2 & alu_op [1:0] $end
$var wire 128 ' b [127:0] $end
$var wire 128 ( result [127:0] $end
$scope begin g_alu_lanes[0] $end
$var parameter 2 ) i $end
$scope module alu_inst $end
$var wire 32 * a [31:0] $end
$var wire 2 + alu_op [1:0] $end
$var wire 32 , b [31:0] $end
$var parameter 2 - OP_ADD $end
$var parameter 2 . OP_AND $end
$var parameter 2 / OP_OR $end
$var parameter 2 0 OP_SUB $end
$var reg 32 1 result [31:0] $end
$upscope $end
$upscope $end
$scope begin g_alu_lanes[1] $end
$var parameter 2 2 i $end
$scope module alu_inst $end
$var wire 32 3 a [31:0] $end
$var wire 2 4 alu_op [1:0] $end
$var wire 32 5 b [31:0] $end
$var parameter 2 6 OP_ADD $end
$var parameter 2 7 OP_AND $end
$var parameter 2 8 OP_OR $end
$var parameter 2 9 OP_SUB $end
$var reg 32 : result [31:0] $end
$upscope $end
$upscope $end
$scope begin g_alu_lanes[2] $end
$var parameter 3 ; i $end
$scope module alu_inst $end
$var wire 32 < a [31:0] $end
$var wire 2 = alu_op [1:0] $end
$var wire 32 > b [31:0] $end
$var parameter 2 ? OP_ADD $end
$var parameter 2 @ OP_AND $end
$var parameter 2 A OP_OR $end
$var parameter 2 B OP_SUB $end
$var reg 32 C result [31:0] $end
$upscope $end
$upscope $end
$scope begin g_alu_lanes[3] $end
$var parameter 3 D i $end
$scope module alu_inst $end
$var wire 32 E a [31:0] $end
$var wire 2 F alu_op [1:0] $end
$var wire 32 G b [31:0] $end
$var parameter 2 H OP_ADD $end
$var parameter 2 I OP_AND $end
$var parameter 2 J OP_OR $end
$var parameter 2 K OP_SUB $end
$var reg 32 L result [31:0] $end
$upscope $end
$upscope $end
$upscope $end
$scope begin $unm_blk_2 $end
$var reg 32 M expected [31:0] $end
$var integer 32 N error_count [31:0] $end
$var integer 32 O i [31:0] $end
$var integer 32 P j [31:0] $end
$upscope $end
$upscope $end
$enddefinitions $end
$comment Show the parameter values. $end
$dumpall
b1 K
b11 J
b10 I
b0 H
b11 D
b1 B
b11 A
b10 @
b0 ?
b10 ;
b1 9
b11 8
b10 7
b0 6
b1 2
b1 0
b11 /
b10 .
b0 -
b0 )
$end
#0
$dumpvars
b0 P
b0 O
b0 N
bx M
b0 L
b0 G
b0 F
b0 E
b0 C
b0 >
b0 =
b0 <
b0 :
b0 5
b0 4
b0 3
b0 1
b0 ,
b0 +
b0 *
b0 (
b0 '
b0 &
b0 %
b0 $
b0 #
b0 "
b0 !
$end
#10000
b10001010000000000 1
b100000000101011000000001 :
b10000110100110010001100100001101 C
b100000000000000000100001101001100100011001000011010000000010000000010101100000000100000000000000010001010000000000 !
b100000000000000000100001101001100100011001000011010000000010000000010101100000000100000000000000010001010000000000 (
b100000000000000000 L
b1001001101110101001000010010 G
b110010110000101000010001100101 E
b11000110110111111001100110001101 >
b10000110101110010111101100001101 <
b110001111100000101011001100011 5
b100100001001101011000001001 3
b1000000100010010101111010000001 ,
b10010010000101010011010100100100 *
b10 #
b10 &
b10 +
b10 4
b10 =
b10 F
b100 P
b1001001101110101001000010010110001101101111110011001100011010011000111110000010101100110001101000000100010010101111010000001 $
b1001001101110101001000010010110001101101111110011001100011010011000111110000010101100110001101000000100010010101111010000001 '
b110010110000101000010001100101100001101011100101111011000011010000010010000100110101100000100110010010000101010011010100100100 "
b110010110000101000010001100101100001101011100101111011000011010000010010000100110101100000100110010010000101010011010100100100 %
#11000
b100000000000000000 M
b100 P
#20000
b11001011101100111101101110010111 1
b10100111101110010111010101010000 :
b11001001001100000000110110010011 C
b1111111010000000000001110010010011000000001101100100111010011110111001011101010101000011001011101100111101101110010111 !
b1111111010000000000001110010010011000000001101100100111010011110111001011101010101000011001011101100111101101110010111 (
b1111111010000000000001 L
b1100010111101111000010011000101 G
b1100011001101110010010011000110 E
b11111100111111011110100111111001 >
b11000110001011011111011110001100 <
b11110110110101000101011111101101 5
b10011110100011011100110100111101 3
b10111011001000111111000101110110 ,
b10000110110101111100110100001101 *
b1 #
b1 &
b1 +
b1 4
b1 =
b1 F
b1100010111101111000010011000101111111001111110111101001111110011111011011010100010101111110110110111011001000111111000101110110 $
b1100010111101111000010011000101111111001111110111101001111110011111011011010100010101111110110110111011001000111111000101110110 '
b1100011001101110010010011000110110001100010110111110111100011001001111010001101110011010011110110000110110101111100110100001101 "
b1100011001101110010010011000110110001100010110111110111100011001001111010001101110011010011110110000110110101111100110100001101 %
b100 P
b1 O
#21000
b1111111010000000000001 M
b100 P
#30000
b110010100000100111001001100101 1
b1001000001101001000000010 :
b1100001001100000000000011000010 C
b1100000000000000100101011000000011000010011000000000000110000100000000100100000110100100000001000110010100000100111001001100101 !
b1100000000000000100101011000000011000010011000000000000110000100000000100100000110100100000001000110010100000100111001001100101 (
b1100000000000000100101011000000 L
b1100010110010100100111011000101 G
b1110100000000000111101011101000 E
b1100111011101101001011011001110 >
b11111001001100000110100111110010 <
b11000111111011001101101110001111 5
b1001001100101101011000010010 3
b111011110100100111001001110111 ,
b11110010101011111111011111100101 *
b10 #
b10 &
b10 +
b10 4
b10 =
b10 F
b1100010110010100100111011000101011001110111011010010110110011101100011111101100110110111000111100111011110100100111001001110111 $
b1100010110010100100111011000101011001110111011010010110110011101100011111101100110110111000111100111011110100100111001001110111 '
b1110100000000000111101011101000111110010011000001101001111100100000100100110010110101100001001011110010101011111111011111100101 "
b1110100000000000111101011101000111110010011000001101001111100100000100100110010110101100001001011110010101011111111011111100101 %
b100 P
b10 O
#31000
b1100000000000000100101011000000 M
b100 P
#40000
b1000111111000101101000010010000 1
b101101111100010000000010 :
b1000101001110000110010010001010 C
b10111010111010111101101101110110010001010011100001100100100010100000000010110111110001000000001001000111111000101101000010010000 !
b10111010111010111101101101110110010001010011100001100100100010100000000010110111110001000000001001000111111000101101000010010000 (
b10111010111010111101101101110110 L
b11010101011110000100010110101010 G
b10010000011001000010000100100000 E
b1000000001110110010001010000000 >
b10000101011100111000011100001010 <
b110001111011110110001001100011 5
b110010101001110010011001100101 3
b10110101010110101100000101101 ,
b1011110100011100010100010111101 *
b1 #
b1 &
b1 +
b1 4
b1 =
b1 F
b11010101011110000100010110101010010000000011101100100010100000000011000111101111011000100110001100010110101010110101100000101101 $
b11010101011110000100010110101010010000000011101100100010100000000011000111101111011000100110001100010110101010110101100000101101 '
b10010000011001000010000100100000100001010111001110000111000010100011001010100111001001100110010101011110100011100010100010111101 "
b10010000011001000010000100100000100001010111001110000111000010100011001010100111001001100110010101011110100011100010100010111101 %
b100 P
b11 O
#41000
b10111010111010111101101101110110 M
b100 P
#50000
b1001000000000011100000010010 1
b101001000001000000000001 :
b100000100001100000100001000001 C
b1000101100000101000000010001000001000011000001000010000010000000010100100000100000000000100001001000000000011100000010010 !
b1000101100000101000000010001000001000011000001000010000010000000010100100000100000000000100001001000000000011100000010010 (
b1000101100000101000000010 L
b1010111010101100011111010101110 G
b1000101110100101000000010 E
b1101010101001100010101011010101 >
b10110101100111111101110101101011 <
b101001101001111101011001010011 5
b110101111000011100000001101 3
b1001100000111011100000010011 ,
b1001011001000000011111010010110 *
b10 #
b10 &
b10 +
b10 4
b10 =
b10 F
b1010111010101100011111010101110011010101010011000101010110101010010100110100111110101100101001100001001100000111011100000010011 $
b1010111010101100011111010101110011010101010011000101010110101010010100110100111110101100101001100001001100000111011100000010011 '
b1000101110100101000000010101101011001111111011101011010110000011010111100001110000000110101001011001000000011111010010110 "
b1000101110100101000000010101101011001111111011101011010110000011010111100001110000000110101001011001000000011111010010110 %
b100 P
b100 O
#51000
b1000101100000101000000010 M
b100 P
#60000
b11010110010000010010100110101100 1
b11111100101100101101001000000 :
b100100110010001000111001001010 C
b100100011010011010111001001001001001001100100010001110010010100001111110010110010110100100000011010110010000010010100110101100 !
b100100011010011010111001001001001001001100100010001110010010100001111110010110010110100100000011010110010000010010100110101100 (
b100100011010011010111001001001 L
b10100000110001001011001101000001 G
b11000101001011100110000110001010 E
b11111001011010001011110111110010 >
b11110001100010100110000111100 <
b1100101011100110000101011001010 5
b10000101000010010110010100001010 3
b10010001100001000100100100100011 ,
b1100111110001010111001011001111 *
b1 #
b1 &
b1 +
b1 4
b1 =
b1 F
b10100000110001001011001101000001111110010110100010111101111100100110010101110011000010101100101010010001100001000100100100100011 $
b10100000110001001011001101000001111110010110100010111101111100100110010101110011000010101100101010010001100001000100100100100011 '
b11000101001011100110000110001010000111100011000101001100001111001000010100001001011001010000101001100111110001010111001011001111 "
b11000101001011100110000110001010000111100011000101001100001111001000010100001001011001010000101001100111110001010111001011001111 %
b100 P
b101 O
#61000
b100100011010011010111001001001 M
b100 P
#70000
b101010110000011000000001 1
b11010000110001110111001110100001 :
b10111010011000010000110101110100 C
b11110011100001001101111111100110101110100110000100001101011101001101000011000111011100111010000100000000101010110000011000000001 !
b11110011100001001101111111100110101110100110000100001101011101001101000011000111011100111010000100000000101010110000011000000001 (
b11110011100001001101111111100110 L
b10010101000011111101110100101010 G
b1011110011101010000001010111100 E
b11010111000101010001001110101110 >
b11100011010010111111100111000110 <
b11011011000000100110010110110110 5
b11110101110001010000110111101011 3
b1000100100010100001001010001001 ,
b10111100001000001111001101111000 *
b0 #
b0 &
b0 +
b0 4
b0 =
b0 F
b10010101000011111101110100101010110101110001010100010011101011101101101100000010011001011011011001000100100010100001001010001001 $
b10010101000011111101110100101010110101110001010100010011101011101101101100000010011001011011011001000100100010100001001010001001 '
b1011110011101010000001010111100111000110100101111111001110001101111010111000101000011011110101110111100001000001111001101111000 "
b1011110011101010000001010111100111000110100101111111001110001101111010111000101000011011110101110111100001000001111001101111000 %
b100 P
b110 O
#71000
b11110011100001001101111111100110 M
b100 P
#80000
b11111010111101111111111111110101 1
b10111111111111100111010101111111 :
b10111111001001110011001101111110 C
b11111010111110111101101111110101101111110010011100110011011111101011111111111110011101010111111111111010111101111111111111110101 !
b11111010111110111101101111110101101111110010011100110011011111101011111111111110011101010111111111111010111101111111111111110101 (
b11111010111110111101101111110101 L
b11111000110110011001101111110001 G
b10001010101010100100101100010101 E
b111111001000110011001001111110 >
b10011101000001100011001100111010 <
b11101110011000110000000111011 5
b10100111111100100101010101001111 3
b11000010111100100100000110000101 ,
b111000100101111011111001110001 *
b11 #
b11 &
b11 +
b11 4
b11 =
b11 F
b11111000110110011001101111110001001111110010001100110010011111100001110111001100011000000011101111000010111100100100000110000101 $
b11111000110110011001101111110001001111110010001100110010011111100001110111001100011000000011101111000010111100100100000110000101 '
b10001010101010100100101100010101100111010000011000110011001110101010011111110010010101010100111100111000100101111011111001110001 "
b10001010101010100100101100010101100111010000011000110011001110101010011111110010010101010100111100111000100101111011111001110001 %
b100 P
b111 O
#81000
b11111010111110111101101111110101 M
b100 P
#90000
b1010111010110010000001010101110 1
b10010111010110101111011100101110 :
b1011000001110110000101010101111 C
b1111110010000011110101011111011010110000011101100001010101011111001011101011010111101110010111001010111010110010000001010101110 !
b1111110010000011110101011111011010110000011101100001010101011111001011101011010111101110010111001010111010110010000001010101110 (
b1111110010000011110101011111011 L
b101110011111011001010001011100 G
b1001111110001000101011010011111 E
b1011011110011010110000010110111 >
b11111100011011011010100111111000 <
b11000111101110011010000110001111 5
b11001111101000010101010110011111 3
b10100110001101011111101101001100 ,
b10110001001000110000011101100010 *
b0 #
b0 &
b0 +
b0 4
b0 =
b0 F
b101110011111011001010001011100010110111100110101100000101101111100011110111001101000011000111110100110001101011111101101001100 $
b101110011111011001010001011100010110111100110101100000101101111100011110111001101000011000111110100110001101011111101101001100 '
b1001111110001000101011010011111111111000110110110101001111110001100111110100001010101011001111110110001001000110000011101100010 "
b1001111110001000101011010011111111111000110110110101001111110001100111110100001010101011001111110110001001000110000011101100010 %
b100 P
b1000 O
#91000
b1111110010000011110101011111011 M
b100 P
#100000
b11100100111111100011011111001001 1
b1101011111111111111111011010111 :
b11101011111001111111111111010111 C
b11100111001111011111111111001110111010111110011111111111110101110110101111111111111111101101011111100100111111100011011111001001 !
b11100111001111011111111111001110111010111110011111111111110101110110101111111111111111101101011111100100111111100011011111001001 (
b11100111001111011111111111001110 L
b1100001001011001100111011000010 G
b10000110000111010111111100001100 E
b11001011001000010010111110010110 >
b101000110001111111110001010001 <
b1101011111111101100000011010111 5
b1101000001000110011111011010000 3
b100100101011100011001001001001 ,
b11000100110111100011011110001001 *
b11 #
b11 &
b11 +
b11 4
b11 =
b11 F
b1100001001011001100111011000010110010110010000100101111100101100110101111111110110000001101011100100100101011100011001001001001 $
b1100001001011001100111011000010110010110010000100101111100101100110101111111110110000001101011100100100101011100011001001001001 '
b10000110000111010111111100001100001010001100011111111100010100010110100000100011001111101101000011000100110111100011011110001001 "
b10000110000111010111111100001100001010001100011111111100010100010110100000100011001111101101000011000100110111100011011110001001 %
b100 P
b1001 O
#101000
b11100111001111011111111111001110 M
b100 P
#110000
b11101111111110111111111111011111 L
b10111110111111011110011101111101 C
b10111111000011011101101101111110 :
b11101111111110111111111111011111101111101111110111100111011111011011111100001101110110110111111010111111111100101111111101111111 !
b11101111111110111111111111011111101111101111110111100111011111011011111100001101110110110111111010111111111100101111111101111111 (
b10111111111100101111111101111111 1
b1101001111010111111011011010011 G
b10001111110100101000111100011111 E
b10011100110110011110011100111001 >
b10110110111001011000000101101101 <
b111111000001010000000001111110 5
b10001001000011001101101100010010 3
b10011110111100101110110100111101 ,
b111011100000100101101001110111 *
b1101001111010111111011011010011100111001101100111100111001110010011111100000101000000000111111010011110111100101110110100111101 $
b1101001111010111111011011010011100111001101100111100111001110010011111100000101000000000111111010011110111100101110110100111101 '
b10001111110100101000111100011111101101101110010110000001011011011000100100001100110110110001001000111011100000100101101001110111 "
b10001111110100101000111100011111101101101110010110000001011011011000100100001100110110110001001000111011100000100101101001110111 %
b100 P
b1010 O
#111000
b11101111111110111111111111011111 M
b100 P
#120000
b10001110001110100010111100011101 1
b10000100100110001001110100001010 :
b11101000111101110100101111010010 C
b11111100001001010010101111111000111010001111011101001011110100101000010010011000100111010000101010001110001110100010111100011101 !
b11111100001001010010101111111000111010001111011101001011110100101000010010011000100111010000101010001110001110100010111100011101 (
b11111100001001010010101111111000 L
b1000111000110100000110010001110 G
b1000011001111110011100010000110 E
b10101100000101010110001101011000 >
b10010101000011001010111100101010 <
b11111111100101010111000111111 5
b10100100100010110100101101001001 3
b10101101110110100101100101011011 ,
b111100000101001000100001111000 *
b1 #
b1 &
b1 +
b1 4
b1 =
b1 F
b1000111000110100000110010001110101011000001010101100011010110000001111111110010101011100011111110101101110110100101100101011011 $
b1000111000110100000110010001110101011000001010101100011010110000001111111110010101011100011111110101101110110100101100101011011 '
b1000011001111110011100010000110100101010000110010101111001010101010010010001011010010110100100100111100000101001000100001111000 "
b1000011001111110011100010000110100101010000110010101111001010101010010010001011010010110100100100111100000101001000100001111000 %
b100 P
b1011 O
#121000
b11111100001001010010101111111000 M
b100 P
#130000
b11111111011111011011110111111110 1
b11111001100111111011011111110011 :
b1011111110110111011101010111111 C
b10101111111110010101111101011111010111111101101110111010101111111111100110011111101101111111001111111111011111011011110111111110 !
b10101111111110010101111101011111010111111101101110111010101111111111100110011111101101111111001111111111011111011011110111111110 (
b10101111111110010101111101011111 L
b10100010001010010000110101000100 G
b101111110110000101011001011111 E
b1011001110100101001001010110011 >
b10111100110011010100000101111 <
b1010001100010111011010010100011 5
b10111001100101100001011101110011 3
b10011011111011011110000100110 ,
b11111101001101011001100111111010 *
b11 #
b11 &
b11 +
b11 4
b11 =
b11 F
b10100010001010010000110101000100010110011101001010010010101100110101000110001011101101001010001100010011011111011011110000100110 $
b10100010001010010000110101000100010110011101001010010010101100110101000110001011101101001010001100010011011111011011110000100110 '
b101111110110000101011001011111000101111001100110101000001011111011100110010110000101110111001111111101001101011001100111111010 "
b101111110110000101011001011111000101111001100110101000001011111011100110010110000101110111001111111101001101011001100111111010 %
b100 P
b1100 O
#131000
b10101111111110010101111101011111 M
b100 P
#140000
b11110010100100100001101111100101 1
b11000010110010001101000110001 :
b1001001011110111011000010011 C
b11011000000101001101001110110000000010010010111101110110000100110001100001011001000110100011000111110010100100100001101111100101 !
b11011000000101001101001110110000000010010010111101110110000100110001100001011001000110100011000111110010100100100001101111100101 (
b11011000000101001101001110110000 L
b1011010100010101110001010110101 G
b110010100111111011011001100101 E
b1101101010100110110110011011010 >
b1110110100000101110001011101101 <
b10010100110011111100000100101001 5
b10101101001010001101101101011010 3
b1110011000010010001101011100110 ,
b1100101100110110011011011001011 *
b1 #
b1 &
b1 +
b1 4
b1 =
b1 F
b1011010100010101110001010110101011011010101001101101100110110101001010011001111110000010010100101110011000010010001101011100110 $
b1011010100010101110001010110101011011010101001101101100110110101001010011001111110000010010100101110011000010010001101011100110 '
b110010100111111011011001100101011101101000001011100010111011011010110100101000110110110101101001100101100110110011011011001011 "
b110010100111111011011001100101011101101000001011100010111011011010110100101000110110110101101001100101100110110011011011001011 %
b100 P
b1101 O
#141000
b11011000000101001101001110110000 M
b100 P
#150000
b10100000111111101111000101000010 L
b1001110100001101101111010011101 C
b11010011011010110000000110100110 :
b10100000111111101111000101000010010011101000011011011110100111011101001101101011000000011010011000011010101111110001101000110101 !
b10100000111111101111000101000010010011101000011011011110100111011101001101101011000000011010011000011010101111110001101000110101 (
b11010101111110001101000110101 1
b1001101010111101011110010011010 G
b11101110010111011010110111011100 E
b10000111011011111100111100001110 >
b11010101111101101010110110101011 <
b10010101000010010000101100101010 5
b1101000011101000000110011010000 3
b10100010001100011111111101000100 ,
b10111100111100010001100101111001 *
b1001101010111101011110010011010100001110110111111001111000011101001010100001001000010110010101010100010001100011111111101000100 $
b1001101010111101011110010011010100001110110111111001111000011101001010100001001000010110010101010100010001100011111111101000100 '
b11101110010111011010110111011100110101011111011010101101101010110110100001110100000011001101000010111100111100010001100101111001 "
b11101110010111011010110111011100110101011111011010101101101010110110100001110100000011001101000010111100111100010001100101111001 %
b100 P
b1110 O
#151000
b10100000111111101111000101000010 M
b100 P
#160000
b1011111001111010000001010111111 L
b101001110000010111101001010100 C
b1110011101000000111001011100111 :
b1011111001111010000001010111111001010011100000101111010010101000111001110100000011100101110011110110110111000100001010101101101 !
b1011111001111010000001010111111001010011100000101111010010101000111001110100000011100101110011110110110111000100001010101101101 (
b10110110111000100001010101101101 1
b10111100110100011000011101111001 G
b11100000011101000101000111000 E
b11011011011011111011100110110110 >
b101001100010011010000001010 <
b110011110110010111011001100111 5
b10100111011110011110100101001110 3
b10101011000011101110110101010110 ,
b1100001111100010000001011000011 *
b10111100110100011000011101111001110110110110111110111001101101100011001111011001011101100110011110101011000011101110110101010110 $
b10111100110100011000011101111001110110110110111110111001101101100011001111011001011101100110011110101011000011101110110101010110 '
b11100000011101000101000111000000001010011000100110100000010101010011101111001111010010100111001100001111100010000001011000011 "
b11100000011101000101000111000000001010011000100110100000010101010011101111001111010010100111001100001111100010000001011000011 %
b100 P
b1111 O
#161000
b1011111001111010000001010111111 M
b100 P
#170000
b10010100001110110001110100100111 1
b101110111101101111011001011101 :
b10100110010000100100000101000 C
b100011010101001101111001000110000101001100100001001000001010000010111011110110111101100101110110010100001110110001110100100111 !
b100011010101001101111001000110000101001100100001001000001010000010111011110110111101100101110110010100001110110001110100100111 (
b100011010101001101111001000110 L
b110110101001000010011001101101 G
b11101100101100001011011111011001 E
b100110111111001101111001001101 >
b11101101110010110110100111011011 <
b101100101101111100101001011001 5
b10001111110010110000000100 3
b11001001110001100101110110010011 ,
b11001010011101001011111110010100 *
b0 #
b0 &
b0 +
b0 4
b0 =
b0 F
b110110101001000010011001101101001001101111110011011110010011010010110010110111110010100101100111001001110001100101110110010011 $
b110110101001000010011001101101001001101111110011011110010011010010110010110111110010100101100111001001110001100101110110010011 '
b11101100101100001011011111011001111011011100101101101001110110110000001000111111001011000000010011001010011101001011111110010100 "
b11101100101100001011011111011001111011011100101101101001110110110000001000111111001011000000010011001010011101001011111110010100 %
b100 P
b10000 O
#171000
b100011010101001101111001000110 M
b100 P
#180000
b11111111001111110110110111111110 1
b11101011100101110111101111010111 :
b11111011111101101111101111110111 C
b11111110111111101011111111111101111110111111011011111011111101111110101110010111011110111101011111111111001111110110110111111110 !
b11111110111111101011111111111101111110111111011011111011111101111110101110010111011110111101011111111111001111110110110111111110 (
b11111110111111101011111111111101 L
b1011010011011101011101010110100 G
b10110100100110000000011101101001 E
b11111011110100100110000111110111 >
b10000010011101001001101100000100 <
b100011000001110001101001000110 5
b11001010100100110111000110010101 3
b11011011000101110010110110110110 ,
b11100101001110110100100111001010 *
b11 #
b11 &
b11 +
b11 4
b11 =
b11 F
b1011010011011101011101010110100111110111101001001100001111101110010001100000111000110100100011011011011000101110010110110110110 $
b1011010011011101011101010110100111110111101001001100001111101110010001100000111000110100100011011011011000101110010110110110110 '
b10110100100110000000011101101001100000100111010010011011000001001100101010010011011100011001010111100101001110110100100111001010 "
b10110100100110000000011101101001100000100111010010011011000001001100101010010011011100011001010111100101001110110100100111001010 %
b100 P
b10001 O
#181000
b11111110111111101011111111111101 M
b100 P
#190000
b10101011000011001101110101010101 1
b1111011001000011100110011110101 :
b10010010101110010010100100100100 C
b10011010001011010111000100110100100101011100100101001001001000111101100100001110011001111010110101011000011001101110101010101 !
b10011010001011010111000100110100100101011100100101001001001000111101100100001110011001111010110101011000011001101110101010101 (
b10011010001011010111000100110 L
b10010100100111100000011100101001 G
b1111110101001111010011011111101 E
b10001110010000010100010100011100 >
b100011101111110010000001000 <
b10111010111001001110000101110 5
b1100011110001010011000011000111 3
b10110100100000000010000101101 ,
b10010100011111001101100100101000 *
b0 #
b0 &
b0 +
b0 4
b0 =
b0 F
b10010100100111100000011100101001100011100100000101000101000111000001011101011100100111000010111000010110100100000000010000101101 $
b10010100100111100000011100101001100011100100000101000101000111000001011101011100100111000010111000010110100100000000010000101101 '
b1111110101001111010011011111101000001000111011111100100000010000110001111000101001100001100011110010100011111001101100100101000 "
b1111110101001111010011011111101000001000111011111100100000010000110001111000101001100001100011110010100011111001101100100101000 %
b100 P
b10010 O
#191000
b10011010001011010111000100110 M
b100 P
#200000
b11101111001101010110111111011110 1
b10111111111111111110011101111111 :
b111001111101011100010001110011 C
b11111111011110111011101111111110001110011111010111000100011100111011111111111111111001110111111111101111001101010110111111011110 !
b11111111011110111011101111111110001110011111010111000100011100111011111111111111111001110111111111101111001101010110111111011110 (
b11111111011110111011101111111110 L
b10101111001110101011001101011110 G
b11011101011100011001100110111010 E
b111001111101010000010001110011 >
b111000010101011100010001110000 <
b10110011010011101010011101100110 5
b11110101101111100011000111101 3
b1101101001101000000100011011010 ,
b11000011001101010110011110000110 *
b11 #
b11 &
b11 +
b11 4
b11 =
b11 F
b10101111001110101011001101011110001110011111010100000100011100111011001101001110101001110110011001101101001101000000100011011010 $
b10101111001110101011001101011110001110011111010100000100011100111011001101001110101001110110011001101101001101000000100011011010 '
b11011101011100011001100110111010001110000101010111000100011100000001111010110111110001100011110111000011001101010110011110000110 "
b11011101011100011001100110111010001110000101010111000100011100000001111010110111110001100011110111000011001101010110011110000110 %
b100 P
b10011 O
#201000
b11111111011110111011101111111110 M
b100 P
#210000
b1000000001000000010000010000 1
b11000100000000000000000110001 :
b11000000001000010010000110000000 C
b10011000001000001101000100110110000000010000100100001100000000001100010000000000000000011000100001000000001000000010000010000 !
b10011000001000001101000100110110000000010000100100001100000000001100010000000000000000011000100001000000001000000010000010000 (
b10011000001000001101000100110 L
b1011011010001100001101010110110 G
b10010011001001011001111100100110 E
b11100000001110010010000111000000 >
b11001011001001110011011110010110 <
b10011011100001110110000100110111 5
b1011100111100000000000010111001 3
b1101001001001111011000011010 ,
b11101010100011100000010111010101 *
b10 #
b10 &
b10 +
b10 4
b10 =
b10 F
b1011011010001100001101010110110111000000011100100100001110000001001101110000111011000010011011100001101001001001111011000011010 $
b1011011010001100001101010110110111000000011100100100001110000001001101110000111011000010011011100001101001001001111011000011010 '
b10010011001001011001111100100110110010110010011100110111100101100101110011110000000000001011100111101010100011100000010111010101 "
b10010011001001011001111100100110110010110010011100110111100101100101110011110000000000001011100111101010100011100000010111010101 %
b100 P
b10100 O
#211000
b10011000001000001101000100110 M
b100 P
#220000
b10110001110000000110011101100010 1
b1111011010111101001101011110110 :
b11010101010100010011011110101010 C
b111010000101100001000001110011110101010101000100110111101010100111101101011110100110101111011010110001110000000110011101100010 !
b111010000101100001000001110011110101010101000100110111101010100111101101011110100110101111011010110001110000000110011101100010 (
b111010000101100001000001110011 L
b1111101001010001110010011111010 G
b10111100111011010010101101111001 E
b1100111110000111011011011001111 >
b1101101100011011000000011011011 <
b10111111010110101001101101111110 5
b10111100000000111111111101111000 3
b11000011011000010101011110000110 ,
b11101110010111110000111111011100 *
b0 #
b0 &
b0 +
b0 4
b0 =
b0 F
b1111101001010001110010011111010011001111100001110110110110011111011111101011010100110110111111011000011011000010101011110000110 $
b1111101001010001110010011111010011001111100001110110110110011111011111101011010100110110111111011000011011000010101011110000110 '
b10111100111011010010101101111001011011011000110110000000110110111011110000000011111111110111100011101110010111110000111111011100 "
b10111100111011010010101101111001011011011000110110000000110110111011110000000011111111110111100011101110010111110000111111011100 %
b100 P
b10101 O
#221000
b111010000101100001000001110011 M
b100 P
#230000
b111010100111101001000001110110 1
b10011011000100111111101100110110 :
b11011111110101111101000111000000 C
b110011111010010001010001101000110111111101011111010001110000001001101100010011111110110011011000111010100111101001000001110110 !
b110011111010010001010001101000110111111101011111010001110000001001101100010011111110110011011000111010100111101001000001110110 (
b110011111010010001010001101000 L
b11100000101100010111010111000001 G
b10100100110101000101000101001 E
b11010101101001000100000110101 >
b11111010100011000101100111110101 <
b101000011000111001011001010000 5
b11000011011101111001000110000110 3
b1010000111101010111100010100001 ,
b10001011100101000000100100010111 *
b1 #
b1 &
b1 +
b1 4
b1 =
b1 F
b11100000101100010111010111000001000110101011010010001000001101010010100001100011100101100101000001010000111101010111100010100001 $
b11100000101100010111010111000001000110101011010010001000001101010010100001100011100101100101000001010000111101010111100010100001 '
b10100100110101000101000101001111110101000110001011001111101011100001101110111100100011000011010001011100101000000100100010111 "
b10100100110101000101000101001111110101000110001011001111101011100001101110111100100011000011010001011100101000000100100010111 %
b100 P
b10110 O
#231000
b110011111010010001010001101000 M
b100 P
